[{"OBJECT_NAME": "CAPELLA-9-WHITNEY", "NORAD_CAT_ID": 55910, "MEAN_MOTION": 14.99271847, "ECCENTRICITY": 0.0009067, "INCLINATION": 43.9991, "RA_OF_ASC_NODE": 244.4088, "ARG_OF_PERICENTER": 156.0492, "MEAN_ANOMALY": 204.0788, "BSTAR": 0.0013163, "EPOCH": "2023-12-27T21:00:03"}, {"OBJECT_NAME": "CAPELLA-6-WHITNEY", "NORAD_CAT_ID": 48605, "MEAN_MOTION": 15.36992166, "ECCENTRICITY": 0.0006978, "INCLINATION": 53.0293, "RA_OF_ASC_NODE": 151.2332, "ARG_OF_PERICENTER": 275.4158, "MEAN_ANOMALY": 84.6048, "BSTAR": 0.0028544000000000004, "EPOCH": "2023-12-28T11:48:20"}, {"OBJECT_NAME": "CAPELLA-8-WHITNEY", "NORAD_CAT_ID": 51071, "MEAN_MOTION": 16.38892911, "ECCENTRICITY": 0.0015575, "INCLINATION": 97.4006, "RA_OF_ASC_NODE": 322.5782, "ARG_OF_PERICENTER": 273.5387, "MEAN_ANOMALY": 175.0653, "BSTAR": 0.0030023, "EPOCH": "2023-09-06T01:34:15"}, {"OBJECT_NAME": "CAPELLA-7-WHITNEY", "NORAD_CAT_ID": 51072, "MEAN_MOTION": 16.44927659, "ECCENTRICITY": 0.0015288, "INCLINATION": 97.3947, "RA_OF_ASC_NODE": 311.3663, "ARG_OF_PERICENTER": 273.4288, "MEAN_ANOMALY": 179.2482, "BSTAR": 0.0011137, "EPOCH": "2023-08-26T19:44:02"}, {"OBJECT_NAME": "CAPELLA-10-WHITNEY", "NORAD_CAT_ID": 55909, "MEAN_MOTION": 14.95890017, "ECCENTRICITY": 0.0009144, "INCLINATION": 43.9994, "RA_OF_ASC_NODE": 246.9297, "ARG_OF_PERICENTER": 166.1646, "MEAN_ANOMALY": 193.9462, "BSTAR": 0.00065599, "EPOCH": "2023-12-27T21:10:20"}, {"OBJECT_NAME": "CAPELLA-11 (ACADIA-1)", "NORAD_CAT_ID": 57693, "MEAN_MOTION": 14.80571571, "ECCENTRICITY": 0.0002549, "INCLINATION": 53.0051, "RA_OF_ASC_NODE": 241.5, "ARG_OF_PERICENTER": 127.5905, "MEAN_ANOMALY": 232.5304, "BSTAR": 0.00045154, "EPOCH": "2026-03-12T20:38:53"}, {"OBJECT_NAME": "CAPELLA-14 (ACADIA-4)", "NORAD_CAT_ID": 59444, "MEAN_MOTION": 15.10713992, "ECCENTRICITY": 0.0004182, "INCLINATION": 45.6047, "RA_OF_ASC_NODE": 40.8166, "ARG_OF_PERICENTER": 138.8002, "MEAN_ANOMALY": 221.32, "BSTAR": 0.0012364000000000001, "EPOCH": "2026-03-13T08:06:00"}, {"OBJECT_NAME": "CAPELLA-13 (ACADIA-3)", "NORAD_CAT_ID": 60419, "MEAN_MOTION": 14.87642553, "ECCENTRICITY": 0.000131, "INCLINATION": 53.0064, "RA_OF_ASC_NODE": 120.2379, "ARG_OF_PERICENTER": 99.2032, "MEAN_ANOMALY": 260.9096, "BSTAR": -0.0007528599999999999, "EPOCH": "2026-03-12T08:31:00"}, {"OBJECT_NAME": "CAPELLA-15 (ACADIA-5)", "NORAD_CAT_ID": 60544, "MEAN_MOTION": 14.92437598, "ECCENTRICITY": 0.0004118, "INCLINATION": 97.6855, "RA_OF_ASC_NODE": 146.8612, "ARG_OF_PERICENTER": 61.8229, "MEAN_ANOMALY": 298.3406, "BSTAR": -0.00029862, "EPOCH": "2026-03-12T13:48:01"}, {"OBJECT_NAME": "CAPELLA-17 (ACADIA-7)", "NORAD_CAT_ID": 64583, "MEAN_MOTION": 14.90912744, "ECCENTRICITY": 0.0004358, "INCLINATION": 97.7566, "RA_OF_ASC_NODE": 187.4545, "ARG_OF_PERICENTER": 319.2015, "MEAN_ANOMALY": 40.8876, "BSTAR": 0.00098, "EPOCH": "2026-03-13T07:55:00"}, {"OBJECT_NAME": "CAPELLA-16 (ACADIA-6)", "NORAD_CAT_ID": 65318, "MEAN_MOTION": 14.93545595, "ECCENTRICITY": 0.0004913, "INCLINATION": 97.74, "RA_OF_ASC_NODE": 149.4795, "ARG_OF_PERICENTER": 185.0813, "MEAN_ANOMALY": 175.0358, "BSTAR": 0.00082972, "EPOCH": "2026-03-13T22:09:56"}, {"OBJECT_NAME": "CAPELLA-19 (ACADIA-9)", "NORAD_CAT_ID": 67384, "MEAN_MOTION": 14.86660787, "ECCENTRICITY": 0.0001275, "INCLINATION": 97.8129, "RA_OF_ASC_NODE": 71.6661, "ARG_OF_PERICENTER": 133.6197, "MEAN_ANOMALY": 226.5125, "BSTAR": 0.00077301, "EPOCH": "2026-03-12T13:06:13"}, {"OBJECT_NAME": "CAPELLA-18 (ACADIA-8)", "NORAD_CAT_ID": 67385, "MEAN_MOTION": 14.88727587, "ECCENTRICITY": 0.0005576, "INCLINATION": 97.801, "RA_OF_ASC_NODE": 73.1268, "ARG_OF_PERICENTER": 78.4894, "MEAN_ANOMALY": 281.6949, "BSTAR": 0.00074085, "EPOCH": "2026-03-13T22:09:17"}, {"OBJECT_NAME": "PLANETUM1", "NORAD_CAT_ID": 52738, "MEAN_MOTION": 16.30442171, "ECCENTRICITY": 0.0009881, "INCLINATION": 97.5537, "RA_OF_ASC_NODE": 110.7236, "ARG_OF_PERICENTER": 292.3042, "MEAN_ANOMALY": 67.7204, "BSTAR": 0.0013242000000000002, "EPOCH": "2024-11-28T20:09:41"}, {"OBJECT_NAME": "GAOFEN-3", "NORAD_CAT_ID": 41727, "MEAN_MOTION": 14.4221702, "ECCENTRICITY": 0.0001688, "INCLINATION": 98.4058, "RA_OF_ASC_NODE": 82.177, "ARG_OF_PERICENTER": 87.1861, "MEAN_ANOMALY": 272.9522, "BSTAR": -3.0976e-06, "EPOCH": "2026-03-13T23:12:22"}, {"OBJECT_NAME": "GAOFEN-3 03", "NORAD_CAT_ID": 52200, "MEAN_MOTION": 14.42207664, "ECCENTRICITY": 0.0001585, "INCLINATION": 98.4113, "RA_OF_ASC_NODE": 82.9211, "ARG_OF_PERICENTER": 91.9814, "MEAN_ANOMALY": 268.1558, "BSTAR": -8.624900000000001e-06, "EPOCH": "2026-03-13T23:22:03"}, {"OBJECT_NAME": "GAOFEN-6", "NORAD_CAT_ID": 43484, "MEAN_MOTION": 14.76603208, "ECCENTRICITY": 0.0013405, "INCLINATION": 97.7865, "RA_OF_ASC_NODE": 139.0605, "ARG_OF_PERICENTER": 122.1169, "MEAN_ANOMALY": 238.1344, "BSTAR": 7.9892e-05, "EPOCH": "2026-03-13T22:18:48"}, {"OBJECT_NAME": "GAOFEN-3 02", "NORAD_CAT_ID": 49495, "MEAN_MOTION": 14.42216649, "ECCENTRICITY": 0.0001467, "INCLINATION": 98.4137, "RA_OF_ASC_NODE": 82.4363, "ARG_OF_PERICENTER": 286.7274, "MEAN_ANOMALY": 73.3755, "BSTAR": -1.2019000000000001e-05, "EPOCH": "2026-03-14T00:01:22"}, {"OBJECT_NAME": "GAOFEN-2", "NORAD_CAT_ID": 40118, "MEAN_MOTION": 14.8077675, "ECCENTRICITY": 0.0007372, "INCLINATION": 98.0215, "RA_OF_ASC_NODE": 137.2317, "ARG_OF_PERICENTER": 171.0983, "MEAN_ANOMALY": 189.0361, "BSTAR": 1.0704e-05, "EPOCH": "2026-03-13T23:16:48"}, {"OBJECT_NAME": "GAOFEN-8", "NORAD_CAT_ID": 40701, "MEAN_MOTION": 15.42612981, "ECCENTRICITY": 0.0009623, "INCLINATION": 97.6943, "RA_OF_ASC_NODE": 260.8431, "ARG_OF_PERICENTER": 172.7159, "MEAN_ANOMALY": 187.4229, "BSTAR": 0.0005817, "EPOCH": "2026-03-13T23:08:38"}, {"OBJECT_NAME": "GAOFEN-7", "NORAD_CAT_ID": 44703, "MEAN_MOTION": 15.21367581, "ECCENTRICITY": 0.00154, "INCLINATION": 97.254, "RA_OF_ASC_NODE": 137.9616, "ARG_OF_PERICENTER": 15.6623, "MEAN_ANOMALY": 344.5087, "BSTAR": 0.00025296000000000004, "EPOCH": "2026-03-13T23:07:59"}, {"OBJECT_NAME": "JILIN-1 GAOFEN 2B", "NORAD_CAT_ID": 44836, "MEAN_MOTION": 15.19512211, "ECCENTRICITY": 0.0012969, "INCLINATION": 97.496, "RA_OF_ASC_NODE": 145.6035, "ARG_OF_PERICENTER": 293.507, "MEAN_ANOMALY": 66.4801, "BSTAR": 0.00035962, "EPOCH": "2026-03-13T23:07:37"}, {"OBJECT_NAME": "GAOFEN-1 02", "NORAD_CAT_ID": 43259, "MEAN_MOTION": 14.76449151, "ECCENTRICITY": 0.0002195, "INCLINATION": 98.0637, "RA_OF_ASC_NODE": 135.4203, "ARG_OF_PERICENTER": 336.3176, "MEAN_ANOMALY": 23.7932, "BSTAR": 9.090000000000001e-05, "EPOCH": "2026-03-13T16:10:22"}, {"OBJECT_NAME": "GAOFEN-1 04", "NORAD_CAT_ID": 43262, "MEAN_MOTION": 14.76444841, "ECCENTRICITY": 0.0001855, "INCLINATION": 98.0639, "RA_OF_ASC_NODE": 135.7601, "ARG_OF_PERICENTER": 75.9314, "MEAN_ANOMALY": 284.2102, "BSTAR": 7.517899999999999e-05, "EPOCH": "2026-03-13T23:11:53"}, {"OBJECT_NAME": "GAOFEN-10R", "NORAD_CAT_ID": 44622, "MEAN_MOTION": 14.83170684, "ECCENTRICITY": 0.0008263, "INCLINATION": 98.0402, "RA_OF_ASC_NODE": 25.9011, "ARG_OF_PERICENTER": 94.7549, "MEAN_ANOMALY": 265.4608, "BSTAR": 0.00022164, "EPOCH": "2026-03-13T22:46:16"}, {"OBJECT_NAME": "JILIN-1 GAOFEN 2A", "NORAD_CAT_ID": 44777, "MEAN_MOTION": 15.36565084, "ECCENTRICITY": 0.0007548, "INCLINATION": 97.5004, "RA_OF_ASC_NODE": 154.6993, "ARG_OF_PERICENTER": 72.4081, "MEAN_ANOMALY": 287.7987, "BSTAR": 0.00049885, "EPOCH": "2026-03-13T22:46:36"}, {"OBJECT_NAME": "JILIN-1 GAOFEN 03D18", "NORAD_CAT_ID": 51844, "MEAN_MOTION": 15.77584928, "ECCENTRICITY": 0.0003896, "INCLINATION": 97.3668, "RA_OF_ASC_NODE": 163.7334, "ARG_OF_PERICENTER": 138.3279, "MEAN_ANOMALY": 221.8285, "BSTAR": 0.0010383, "EPOCH": "2026-03-12T06:23:35"}, {"OBJECT_NAME": "GAOFEN DUOMO (GFDM)", "NORAD_CAT_ID": 45856, "MEAN_MOTION": 14.76849797, "ECCENTRICITY": 0.0011845, "INCLINATION": 97.7861, "RA_OF_ASC_NODE": 136.2514, "ARG_OF_PERICENTER": 26.2921, "MEAN_ANOMALY": 333.8888, "BSTAR": 0.00016078999999999998, "EPOCH": "2026-03-13T22:43:13"}, {"OBJECT_NAME": "JILIN-1 GAOFEN 4A", "NORAD_CAT_ID": 52388, "MEAN_MOTION": 16.28950252, "ECCENTRICITY": 0.000805, "INCLINATION": 97.4754, "RA_OF_ASC_NODE": 100.0865, "ARG_OF_PERICENTER": 290.668, "MEAN_ANOMALY": 69.375, "BSTAR": 0.0010643, "EPOCH": "2025-12-16T07:00:53"}, {"OBJECT_NAME": "JILIN-1 GAOFEN 3D03", "NORAD_CAT_ID": 49006, "MEAN_MOTION": 15.81878461, "ECCENTRICITY": 0.0001474, "INCLINATION": 97.3008, "RA_OF_ASC_NODE": 150.2487, "ARG_OF_PERICENTER": 150.7775, "MEAN_ANOMALY": 209.3576, "BSTAR": 0.0011672, "EPOCH": "2026-03-13T23:41:57"}, {"OBJECT_NAME": "GAOFEN-1 03", "NORAD_CAT_ID": 43260, "MEAN_MOTION": 14.76428287, "ECCENTRICITY": 0.0003234, "INCLINATION": 98.0626, "RA_OF_ASC_NODE": 135.6052, "ARG_OF_PERICENTER": 39.7747, "MEAN_ANOMALY": 320.3699, "BSTAR": 0.00015166, "EPOCH": "2026-03-13T23:46:47"}, {"OBJECT_NAME": "GAOFEN-5 02", "NORAD_CAT_ID": 49122, "MEAN_MOTION": 14.57725614, "ECCENTRICITY": 1.09e-05, "INCLINATION": 98.2672, "RA_OF_ASC_NODE": 147.9575, "ARG_OF_PERICENTER": 265.6614, "MEAN_ANOMALY": 94.4572, "BSTAR": 4.4049000000000005e-05, "EPOCH": "2026-03-13T23:40:13"}, {"OBJECT_NAME": "JILIN-1 GAOFEN 3B", "NORAD_CAT_ID": 46454, "MEAN_MOTION": 15.81348232, "ECCENTRICITY": 0.0003185, "INCLINATION": 97.2358, "RA_OF_ASC_NODE": 130.4491, "ARG_OF_PERICENTER": 144.1208, "MEAN_ANOMALY": 216.0275, "BSTAR": 0.0010368, "EPOCH": "2026-03-13T16:43:21"}, {"OBJECT_NAME": "JILIN-1 GAOFEN 03D54", "NORAD_CAT_ID": 54254, "MEAN_MOTION": 15.69110286, "ECCENTRICITY": 0.0003038, "INCLINATION": 97.6018, "RA_OF_ASC_NODE": 216.0779, "ARG_OF_PERICENTER": 304.0613, "MEAN_ANOMALY": 56.036, "BSTAR": 0.0009132400000000001, "EPOCH": "2026-03-13T22:32:23"}, {"OBJECT_NAME": "ISS (ZARYA)", "NORAD_CAT_ID": 25544, "MEAN_MOTION": 15.48633802, "ECCENTRICITY": 0.0007884, "INCLINATION": 51.6324, "RA_OF_ASC_NODE": 52.4887, "ARG_OF_PERICENTER": 189.2977, "MEAN_ANOMALY": 170.7866, "BSTAR": 0.00022432, "EPOCH": "2026-03-13T16:59:24"}, {"OBJECT_NAME": "ISS (NAUKA)", "NORAD_CAT_ID": 49044, "MEAN_MOTION": 15.48633802, "ECCENTRICITY": 0.0007884, "INCLINATION": 51.6324, "RA_OF_ASC_NODE": 52.4887, "ARG_OF_PERICENTER": 189.2977, "MEAN_ANOMALY": 170.7866, "BSTAR": 0.00022432, "EPOCH": "2026-03-13T16:59:24"}, {"OBJECT_NAME": "SWISSCUBE", "NORAD_CAT_ID": 35932, "MEAN_MOTION": 14.62272355, "ECCENTRICITY": 0.000737, "INCLINATION": 98.4096, "RA_OF_ASC_NODE": 339.2128, "ARG_OF_PERICENTER": 140.2287, "MEAN_ANOMALY": 219.9456, "BSTAR": 0.00027243, "EPOCH": "2026-03-13T23:50:57"}, {"OBJECT_NAME": "AISSAT 1", "NORAD_CAT_ID": 36797, "MEAN_MOTION": 14.96917404, "ECCENTRICITY": 0.0009347, "INCLINATION": 98.1018, "RA_OF_ASC_NODE": 328.8398, "ARG_OF_PERICENTER": 20.3465, "MEAN_ANOMALY": 339.8126, "BSTAR": 0.00026985999999999997, "EPOCH": "2026-03-13T23:18:08"}, {"OBJECT_NAME": "AISSAT 2", "NORAD_CAT_ID": 40075, "MEAN_MOTION": 14.8560182, "ECCENTRICITY": 0.000478, "INCLINATION": 98.3401, "RA_OF_ASC_NODE": 268.4723, "ARG_OF_PERICENTER": 335.0232, "MEAN_ANOMALY": 25.0749, "BSTAR": 0.00040707, "EPOCH": "2023-12-28T11:59:02"}, {"OBJECT_NAME": "ISS OBJECT XK", "NORAD_CAT_ID": 65731, "MEAN_MOTION": 16.39076546, "ECCENTRICITY": 0.0002464, "INCLINATION": 51.6052, "RA_OF_ASC_NODE": 44.2508, "ARG_OF_PERICENTER": 211.8886, "MEAN_ANOMALY": 148.1991, "BSTAR": 0.00075547, "EPOCH": "2026-03-09T22:15:28"}, {"OBJECT_NAME": "ISS OBJECT XU", "NORAD_CAT_ID": 66908, "MEAN_MOTION": 15.70686547, "ECCENTRICITY": 0.0004897, "INCLINATION": 51.6245, "RA_OF_ASC_NODE": 46.3387, "ARG_OF_PERICENTER": 107.7206, "MEAN_ANOMALY": 252.4326, "BSTAR": 0.0013009999999999999, "EPOCH": "2026-03-13T11:07:47"}, {"OBJECT_NAME": "OUTPOST MISSION 2", "NORAD_CAT_ID": 58334, "MEAN_MOTION": 15.51046817, "ECCENTRICITY": 0.0006981, "INCLINATION": 97.3968, "RA_OF_ASC_NODE": 162.7831, "ARG_OF_PERICENTER": 111.1455, "MEAN_ANOMALY": 249.0543, "BSTAR": 0.00065889, "EPOCH": "2026-03-13T22:52:24"}, {"OBJECT_NAME": "ISS (UNITY)", "NORAD_CAT_ID": 25575, "MEAN_MOTION": 15.48633802, "ECCENTRICITY": 0.0007884, "INCLINATION": 51.6324, "RA_OF_ASC_NODE": 52.4887, "ARG_OF_PERICENTER": 189.2977, "MEAN_ANOMALY": 170.7866, "BSTAR": 0.00022432, "EPOCH": "2026-03-13T16:59:24"}, {"OBJECT_NAME": "ISS OBJECT YE", "NORAD_CAT_ID": 67688, "MEAN_MOTION": 15.52874098, "ECCENTRICITY": 0.0008075, "INCLINATION": 51.6312, "RA_OF_ASC_NODE": 53.6814, "ARG_OF_PERICENTER": 164.1724, "MEAN_ANOMALY": 195.952, "BSTAR": 0.0008688000000000001, "EPOCH": "2026-03-13T07:47:10"}, {"OBJECT_NAME": "ISS DEB", "NORAD_CAT_ID": 56434, "MEAN_MOTION": 16.34589017, "ECCENTRICITY": 0.0007268, "INCLINATION": 51.614, "RA_OF_ASC_NODE": 110.8216, "ARG_OF_PERICENTER": 312.4976, "MEAN_ANOMALY": 47.5434, "BSTAR": 0.0007953900000000001, "EPOCH": "2023-12-17T13:53:44"}, {"OBJECT_NAME": "ISS DEB [SPX-28 IPA FSE]", "NORAD_CAT_ID": 57212, "MEAN_MOTION": 16.42826151, "ECCENTRICITY": 0.0005882, "INCLINATION": 51.6078, "RA_OF_ASC_NODE": 38.878, "ARG_OF_PERICENTER": 256.2665, "MEAN_ANOMALY": 278.8784, "BSTAR": 0.00035698999999999995, "EPOCH": "2024-05-22T10:35:37"}, {"OBJECT_NAME": "ISS DEB", "NORAD_CAT_ID": 58174, "MEAN_MOTION": 16.3176295, "ECCENTRICITY": 0.0009401, "INCLINATION": 51.6127, "RA_OF_ASC_NODE": 333.6363, "ARG_OF_PERICENTER": 246.0894, "MEAN_ANOMALY": 113.9145, "BSTAR": 0.001226, "EPOCH": "2024-03-28T18:25:22"}, {"OBJECT_NAME": "ISS DEB", "NORAD_CAT_ID": 58203, "MEAN_MOTION": 15.98175731, "ECCENTRICITY": 0.0014888, "INCLINATION": 51.6276, "RA_OF_ASC_NODE": 303.0132, "ARG_OF_PERICENTER": 126.3295, "MEAN_ANOMALY": 233.9091, "BSTAR": 0.0096833, "EPOCH": "2023-11-14T05:06:41"}, {"OBJECT_NAME": "ISS DEB", "NORAD_CAT_ID": 58229, "MEAN_MOTION": 16.43977649, "ECCENTRICITY": 0.0006009, "INCLINATION": 51.6071, "RA_OF_ASC_NODE": 235.9974, "ARG_OF_PERICENTER": 315.3037, "MEAN_ANOMALY": 44.7506, "BSTAR": 0.00037573, "EPOCH": "2024-06-26T14:41:28"}, {"OBJECT_NAME": "ISS DEB", "NORAD_CAT_ID": 62376, "MEAN_MOTION": 16.23766836, "ECCENTRICITY": 0.0010647, "INCLINATION": 51.6124, "RA_OF_ASC_NODE": 290.5973, "ARG_OF_PERICENTER": 277.8505, "MEAN_ANOMALY": 82.1305, "BSTAR": 0.0017468, "EPOCH": "2025-04-05T18:57:57"}, {"OBJECT_NAME": "ISS (ZVEZDA)", "NORAD_CAT_ID": 26400, "MEAN_MOTION": 15.48633802, "ECCENTRICITY": 0.0007884, "INCLINATION": 51.6324, "RA_OF_ASC_NODE": 52.4887, "ARG_OF_PERICENTER": 189.2977, "MEAN_ANOMALY": 170.7866, "BSTAR": 0.00022432, "EPOCH": "2026-03-13T16:59:24"}, {"OBJECT_NAME": "ISS (DESTINY)", "NORAD_CAT_ID": 26700, "MEAN_MOTION": 15.48633802, "ECCENTRICITY": 0.0007884, "INCLINATION": 51.6324, "RA_OF_ASC_NODE": 52.4887, "ARG_OF_PERICENTER": 189.2977, "MEAN_ANOMALY": 170.7866, "BSTAR": 0.00022432, "EPOCH": "2026-03-13T16:59:24"}, {"OBJECT_NAME": "ISS OBJECT XT", "NORAD_CAT_ID": 66907, "MEAN_MOTION": 15.70505609, "ECCENTRICITY": 0.0004699, "INCLINATION": 51.6247, "RA_OF_ASC_NODE": 47.0068, "ARG_OF_PERICENTER": 104.7322, "MEAN_ANOMALY": 255.4197, "BSTAR": 0.0013594999999999998, "EPOCH": "2026-03-13T08:07:34"}, {"OBJECT_NAME": "ISS OBJECT XW", "NORAD_CAT_ID": 66910, "MEAN_MOTION": 15.69697037, "ECCENTRICITY": 0.0005316, "INCLINATION": 51.6244, "RA_OF_ASC_NODE": 47.6269, "ARG_OF_PERICENTER": 107.7849, "MEAN_ANOMALY": 252.3729, "BSTAR": 0.0012699, "EPOCH": "2026-03-13T04:59:13"}, {"OBJECT_NAME": "ICEYE-X4", "NORAD_CAT_ID": 44390, "MEAN_MOTION": 15.27095253, "ECCENTRICITY": 0.001218, "INCLINATION": 97.8885, "RA_OF_ASC_NODE": 100.4161, "ARG_OF_PERICENTER": 277.9702, "MEAN_ANOMALY": 82.0154, "BSTAR": 0.0005035300000000001, "EPOCH": "2026-03-13T23:49:55"}, {"OBJECT_NAME": "ICEYE-X9", "NORAD_CAT_ID": 47506, "MEAN_MOTION": 15.28271202, "ECCENTRICITY": 0.0008413, "INCLINATION": 97.3622, "RA_OF_ASC_NODE": 54.3082, "ARG_OF_PERICENTER": 126.886, "MEAN_ANOMALY": 233.3152, "BSTAR": 0.0010076, "EPOCH": "2023-12-28T11:08:25"}, {"OBJECT_NAME": "XR-1 (ICEYE-X10)", "NORAD_CAT_ID": 47507, "MEAN_MOTION": 15.22197725, "ECCENTRICITY": 0.001392, "INCLINATION": 97.3689, "RA_OF_ASC_NODE": 55.932, "ARG_OF_PERICENTER": 134.347, "MEAN_ANOMALY": 225.891, "BSTAR": 0.00062135, "EPOCH": "2023-12-28T04:01:27"}, {"OBJECT_NAME": "ICEYE-X8", "NORAD_CAT_ID": 47510, "MEAN_MOTION": 15.26805421, "ECCENTRICITY": 0.0007492, "INCLINATION": 97.3641, "RA_OF_ASC_NODE": 54.4014, "ARG_OF_PERICENTER": 124.0674, "MEAN_ANOMALY": 236.1278, "BSTAR": 0.00062244, "EPOCH": "2023-12-28T10:34:23"}, {"OBJECT_NAME": "ICEYE-X17", "NORAD_CAT_ID": 52762, "MEAN_MOTION": 15.2124607, "ECCENTRICITY": 0.0013644, "INCLINATION": 97.5558, "RA_OF_ASC_NODE": 120.8021, "ARG_OF_PERICENTER": 1.6767, "MEAN_ANOMALY": 358.4512, "BSTAR": 0.00057881, "EPOCH": "2023-12-28T09:08:20"}, {"OBJECT_NAME": "ICEYE-X55", "NORAD_CAT_ID": 64581, "MEAN_MOTION": 14.94549859, "ECCENTRICITY": 0.0002024, "INCLINATION": 97.7609, "RA_OF_ASC_NODE": 188.6379, "ARG_OF_PERICENTER": 316.5225, "MEAN_ANOMALY": 43.5835, "BSTAR": 0.00046989, "EPOCH": "2026-03-13T21:59:46"}, {"OBJECT_NAME": "ICEYE-X33", "NORAD_CAT_ID": 60548, "MEAN_MOTION": 15.01177965, "ECCENTRICITY": 0.0006008, "INCLINATION": 97.7037, "RA_OF_ASC_NODE": 152.4523, "ARG_OF_PERICENTER": 111.5308, "MEAN_ANOMALY": 248.6557, "BSTAR": 0.00044679, "EPOCH": "2026-03-13T15:27:23"}, {"OBJECT_NAME": "ICEYE-X21", "NORAD_CAT_ID": 55049, "MEAN_MOTION": 15.77464515, "ECCENTRICITY": 0.0003402, "INCLINATION": 97.3379, "RA_OF_ASC_NODE": 152.0526, "ARG_OF_PERICENTER": 60.6638, "MEAN_ANOMALY": 299.4968, "BSTAR": 0.00056355, "EPOCH": "2026-03-13T21:55:17"}, {"OBJECT_NAME": "ICEYE-X7", "NORAD_CAT_ID": 46496, "MEAN_MOTION": 15.2927708, "ECCENTRICITY": 0.0006409, "INCLINATION": 97.7409, "RA_OF_ASC_NODE": 35.3598, "ARG_OF_PERICENTER": 315.7508, "MEAN_ANOMALY": 44.3218, "BSTAR": 0.00054143, "EPOCH": "2026-03-13T22:40:15"}, {"OBJECT_NAME": "ICEYE-X53", "NORAD_CAT_ID": 64584, "MEAN_MOTION": 15.0089958, "ECCENTRICITY": 0.000134, "INCLINATION": 97.7419, "RA_OF_ASC_NODE": 190.1145, "ARG_OF_PERICENTER": 196.1905, "MEAN_ANOMALY": 163.9276, "BSTAR": 0.00046425, "EPOCH": "2026-03-13T22:55:07"}, {"OBJECT_NAME": "ICEYE-X40", "NORAD_CAT_ID": 60549, "MEAN_MOTION": 14.97582986, "ECCENTRICITY": 0.0005926, "INCLINATION": 97.6865, "RA_OF_ASC_NODE": 150.671, "ARG_OF_PERICENTER": 54.553, "MEAN_ANOMALY": 305.6244, "BSTAR": 0.00028059, "EPOCH": "2026-03-13T15:13:46"}, {"OBJECT_NAME": "ICEYE-X49", "NORAD_CAT_ID": 62384, "MEAN_MOTION": 15.1206309, "ECCENTRICITY": 0.0002244, "INCLINATION": 44.9973, "RA_OF_ASC_NODE": 147.332, "ARG_OF_PERICENTER": 261.341, "MEAN_ANOMALY": 98.7213, "BSTAR": 0.0005264600000000001, "EPOCH": "2026-03-13T14:29:43"}, {"OBJECT_NAME": "ICEYE-X27", "NORAD_CAT_ID": 55062, "MEAN_MOTION": 15.21915655, "ECCENTRICITY": 0.0013054, "INCLINATION": 97.4564, "RA_OF_ASC_NODE": 59.6015, "ARG_OF_PERICENTER": 58.5293, "MEAN_ANOMALY": 301.7217, "BSTAR": 0.00058627, "EPOCH": "2023-12-28T03:09:32"}, {"OBJECT_NAME": "ICEYE-X6", "NORAD_CAT_ID": 46497, "MEAN_MOTION": 15.039316, "ECCENTRICITY": 0.0008591, "INCLINATION": 98.0932, "RA_OF_ASC_NODE": 62.1157, "ARG_OF_PERICENTER": 56.1732, "MEAN_ANOMALY": 304.031, "BSTAR": 0.00023758, "EPOCH": "2026-03-13T22:26:47"}, {"OBJECT_NAME": "ICEYE-X47", "NORAD_CAT_ID": 62389, "MEAN_MOTION": 15.12292506, "ECCENTRICITY": 0.0001244, "INCLINATION": 44.9953, "RA_OF_ASC_NODE": 145.4322, "ARG_OF_PERICENTER": 284.6191, "MEAN_ANOMALY": 75.4548, "BSTAR": 0.00041522, "EPOCH": "2026-03-13T22:14:04"}, {"OBJECT_NAME": "ICEYE-X30", "NORAD_CAT_ID": 56947, "MEAN_MOTION": 15.73665321, "ECCENTRICITY": 0.0005197, "INCLINATION": 97.57, "RA_OF_ASC_NODE": 224.5987, "ARG_OF_PERICENTER": 272.4893, "MEAN_ANOMALY": 87.5776, "BSTAR": 0.00087825, "EPOCH": "2026-03-13T23:00:43"}, {"OBJECT_NAME": "ICEYE-X42", "NORAD_CAT_ID": 62698, "MEAN_MOTION": 14.91846966, "ECCENTRICITY": 0.0001233, "INCLINATION": 97.7388, "RA_OF_ASC_NODE": 152.9884, "ARG_OF_PERICENTER": 114.5043, "MEAN_ANOMALY": 245.6305, "BSTAR": 0.00032354, "EPOCH": "2026-03-13T23:08:06"}, {"OBJECT_NAME": "ICEYE-X41", "NORAD_CAT_ID": 62700, "MEAN_MOTION": 14.96111406, "ECCENTRICITY": 0.0001677, "INCLINATION": 97.7117, "RA_OF_ASC_NODE": 153.9314, "ARG_OF_PERICENTER": 40.0054, "MEAN_ANOMALY": 320.1291, "BSTAR": 0.00033944000000000004, "EPOCH": "2026-03-13T23:39:00"}, {"OBJECT_NAME": "ICEYE-X26", "NORAD_CAT_ID": 56961, "MEAN_MOTION": 15.73858643, "ECCENTRICITY": 9.1e-05, "INCLINATION": 97.5762, "RA_OF_ASC_NODE": 228.9322, "ARG_OF_PERICENTER": 244.947, "MEAN_ANOMALY": 115.1699, "BSTAR": 0.00051425, "EPOCH": "2026-03-13T22:45:47"}, {"OBJECT_NAME": "ICEYE-X45", "NORAD_CAT_ID": 62705, "MEAN_MOTION": 15.00865736, "ECCENTRICITY": 9.87e-05, "INCLINATION": 97.8062, "RA_OF_ASC_NODE": 158.3012, "ARG_OF_PERICENTER": 72.3822, "MEAN_ANOMALY": 287.7509, "BSTAR": 0.00031790000000000003, "EPOCH": "2026-03-13T04:34:44"}, {"OBJECT_NAME": "YAOGAN-29", "NORAD_CAT_ID": 41038, "MEAN_MOTION": 14.83002272, "ECCENTRICITY": 0.0001638, "INCLINATION": 98.0146, "RA_OF_ASC_NODE": 101.4189, "ARG_OF_PERICENTER": 30.4553, "MEAN_ANOMALY": 329.6755, "BSTAR": 0.00011476, "EPOCH": "2026-03-13T23:27:57"}, {"OBJECT_NAME": "YAOGAN-3", "NORAD_CAT_ID": 32289, "MEAN_MOTION": 14.90384748, "ECCENTRICITY": 0.0001556, "INCLINATION": 97.8274, "RA_OF_ASC_NODE": 103.8011, "ARG_OF_PERICENTER": 82.5153, "MEAN_ANOMALY": 277.6242, "BSTAR": 0.00015498, "EPOCH": "2026-03-14T00:08:30"}, {"OBJECT_NAME": "YAOGAN-4", "NORAD_CAT_ID": 33446, "MEAN_MOTION": 14.82990653, "ECCENTRICITY": 0.0015102, "INCLINATION": 97.9248, "RA_OF_ASC_NODE": 6.5617, "ARG_OF_PERICENTER": 28.3811, "MEAN_ANOMALY": 331.8222, "BSTAR": 0.00019828, "EPOCH": "2026-03-13T07:06:17"}, {"OBJECT_NAME": "YAOGAN-7", "NORAD_CAT_ID": 36110, "MEAN_MOTION": 14.77900526, "ECCENTRICITY": 0.0024434, "INCLINATION": 98.0203, "RA_OF_ASC_NODE": 319.3604, "ARG_OF_PERICENTER": 349.6706, "MEAN_ANOMALY": 10.3999, "BSTAR": 0.00011518, "EPOCH": "2026-03-13T23:13:20"}, {"OBJECT_NAME": "YAOGAN-21", "NORAD_CAT_ID": 40143, "MEAN_MOTION": 15.2500039, "ECCENTRICITY": 0.0009985, "INCLINATION": 97.1615, "RA_OF_ASC_NODE": 117.3514, "ARG_OF_PERICENTER": 74.4879, "MEAN_ANOMALY": 285.7462, "BSTAR": 0.0003128, "EPOCH": "2026-03-13T23:54:32"}, {"OBJECT_NAME": "YAOGAN-10", "NORAD_CAT_ID": 36834, "MEAN_MOTION": 14.85031759, "ECCENTRICITY": 0.0001558, "INCLINATION": 97.9083, "RA_OF_ASC_NODE": 97.1597, "ARG_OF_PERICENTER": 88.1696, "MEAN_ANOMALY": 328.1159, "BSTAR": 0.00020204, "EPOCH": "2026-03-14T00:26:33"}, {"OBJECT_NAME": "YAOGAN-23", "NORAD_CAT_ID": 40305, "MEAN_MOTION": 16.38800959, "ECCENTRICITY": 0.000344, "INCLINATION": 97.6653, "RA_OF_ASC_NODE": 349.5059, "ARG_OF_PERICENTER": 254.7314, "MEAN_ANOMALY": 115.2384, "BSTAR": 0.00072463, "EPOCH": "2024-12-12T06:42:04"}, {"OBJECT_NAME": "YAOGAN-12", "NORAD_CAT_ID": 37875, "MEAN_MOTION": 15.25448863, "ECCENTRICITY": 0.000959, "INCLINATION": 97.1283, "RA_OF_ASC_NODE": 116.0536, "ARG_OF_PERICENTER": 194.3554, "MEAN_ANOMALY": 165.7414, "BSTAR": 0.00020944, "EPOCH": "2026-03-13T23:41:58"}, {"OBJECT_NAME": "YAOGAN-13", "NORAD_CAT_ID": 37941, "MEAN_MOTION": 16.37208404, "ECCENTRICITY": 0.0005273, "INCLINATION": 97.6847, "RA_OF_ASC_NODE": 66.5996, "ARG_OF_PERICENTER": 226.2633, "MEAN_ANOMALY": 199.5818, "BSTAR": 0.00080897, "EPOCH": "2025-02-22T04:56:09"}, {"OBJECT_NAME": "YAOGAN-31 01A", "NORAD_CAT_ID": 43275, "MEAN_MOTION": 13.45452989, "ECCENTRICITY": 0.0267109, "INCLINATION": 63.398, "RA_OF_ASC_NODE": 336.1881, "ARG_OF_PERICENTER": 7.1349, "MEAN_ANOMALY": 353.3361, "BSTAR": 1.1273e-06, "EPOCH": "2026-03-14T00:03:39"}, {"OBJECT_NAME": "YAOGAN-31 01B", "NORAD_CAT_ID": 43276, "MEAN_MOTION": 13.45449081, "ECCENTRICITY": 0.0267122, "INCLINATION": 63.3982, "RA_OF_ASC_NODE": 336.1885, "ARG_OF_PERICENTER": 7.093, "MEAN_ANOMALY": 353.3758, "BSTAR": 5.9414000000000004e-05, "EPOCH": "2026-03-14T00:04:56"}, {"OBJECT_NAME": "YAOGAN-31 01C", "NORAD_CAT_ID": 43277, "MEAN_MOTION": 13.45433034, "ECCENTRICITY": 0.0267067, "INCLINATION": 63.3991, "RA_OF_ASC_NODE": 335.5353, "ARG_OF_PERICENTER": 6.8355, "MEAN_ANOMALY": 353.6199, "BSTAR": -4.8049e-05, "EPOCH": "2026-03-14T00:07:12"}, {"OBJECT_NAME": "YAOGAN-30 06A", "NORAD_CAT_ID": 44449, "MEAN_MOTION": 15.02133353, "ECCENTRICITY": 0.00037, "INCLINATION": 34.9928, "RA_OF_ASC_NODE": 191.5518, "ARG_OF_PERICENTER": 175.6657, "MEAN_ANOMALY": 184.4083, "BSTAR": 0.00026314, "EPOCH": "2026-03-13T17:58:19"}, {"OBJECT_NAME": "YAOGAN-30 06B", "NORAD_CAT_ID": 44450, "MEAN_MOTION": 15.02122328, "ECCENTRICITY": 0.0009262, "INCLINATION": 34.9916, "RA_OF_ASC_NODE": 190.8407, "ARG_OF_PERICENTER": 315.6605, "MEAN_ANOMALY": 44.3361, "BSTAR": 0.00028546, "EPOCH": "2026-03-13T19:04:54"}, {"OBJECT_NAME": "YAOGAN-30 03A", "NORAD_CAT_ID": 43028, "MEAN_MOTION": 15.02274662, "ECCENTRICITY": 0.0002217, "INCLINATION": 34.9941, "RA_OF_ASC_NODE": 133.0268, "ARG_OF_PERICENTER": 207.1099, "MEAN_ANOMALY": 152.9493, "BSTAR": 0.00029570000000000003, "EPOCH": "2026-03-13T14:23:34"}, {"OBJECT_NAME": "YAOGAN-34 02", "NORAD_CAT_ID": 52084, "MEAN_MOTION": 13.45429288, "ECCENTRICITY": 0.0043567, "INCLINATION": 63.3959, "RA_OF_ASC_NODE": 85.7443, "ARG_OF_PERICENTER": 351.6967, "MEAN_ANOMALY": 8.3333, "BSTAR": 5.2638e-05, "EPOCH": "2026-03-13T23:06:41"}, {"OBJECT_NAME": "YAOGAN-30 06C", "NORAD_CAT_ID": 44451, "MEAN_MOTION": 15.02204198, "ECCENTRICITY": 0.0001127, "INCLINATION": 34.9926, "RA_OF_ASC_NODE": 190.8564, "ARG_OF_PERICENTER": 269.6978, "MEAN_ANOMALY": 90.36, "BSTAR": 0.00028075, "EPOCH": "2026-03-13T18:31:13"}, {"OBJECT_NAME": "YAOGAN-30 03B", "NORAD_CAT_ID": 43029, "MEAN_MOTION": 15.02152547, "ECCENTRICITY": 0.0002692, "INCLINATION": 34.9936, "RA_OF_ASC_NODE": 131.1056, "ARG_OF_PERICENTER": 131.7298, "MEAN_ANOMALY": 228.3641, "BSTAR": 0.00019784, "EPOCH": "2026-03-13T20:21:13"}, {"OBJECT_NAME": "YAOGAN-34 01", "NORAD_CAT_ID": 48340, "MEAN_MOTION": 13.45464033, "ECCENTRICITY": 0.0079282, "INCLINATION": 63.4044, "RA_OF_ASC_NODE": 30.9154, "ARG_OF_PERICENTER": 356.7631, "MEAN_ANOMALY": 3.2873, "BSTAR": 0.00012672, "EPOCH": "2026-03-13T23:46:55"}, {"OBJECT_NAME": "YAOGAN-30 03C", "NORAD_CAT_ID": 43030, "MEAN_MOTION": 15.02202777, "ECCENTRICITY": 0.0002654, "INCLINATION": 34.9945, "RA_OF_ASC_NODE": 132.4019, "ARG_OF_PERICENTER": 283.5763, "MEAN_ANOMALY": 76.4649, "BSTAR": 0.00028654, "EPOCH": "2026-03-13T15:02:11"}, {"OBJECT_NAME": "WORLDVIEW-3 (WV-3)", "NORAD_CAT_ID": 40115, "MEAN_MOTION": 14.84845969, "ECCENTRICITY": 2.33e-05, "INCLINATION": 97.8627, "RA_OF_ASC_NODE": 149.0901, "ARG_OF_PERICENTER": 180.2093, "MEAN_ANOMALY": 179.9122, "BSTAR": 0.00013739, "EPOCH": "2026-03-13T22:53:12"}, {"OBJECT_NAME": "WORLDVIEW-2 (WV-2)", "NORAD_CAT_ID": 35946, "MEAN_MOTION": 14.37912466, "ECCENTRICITY": 0.0005217, "INCLINATION": 98.4686, "RA_OF_ASC_NODE": 147.7074, "ARG_OF_PERICENTER": 134.8366, "MEAN_ANOMALY": 225.3246, "BSTAR": 6.7026e-05, "EPOCH": "2026-03-13T21:38:50"}, {"OBJECT_NAME": "WORLDVIEW-1 (WV-1)", "NORAD_CAT_ID": 32060, "MEAN_MOTION": 15.24615389, "ECCENTRICITY": 0.0003347, "INCLINATION": 97.3824, "RA_OF_ASC_NODE": 194.0222, "ARG_OF_PERICENTER": 128.0866, "MEAN_ANOMALY": 232.0674, "BSTAR": 0.00036453, "EPOCH": "2026-03-13T21:39:56"}, {"OBJECT_NAME": "GEOEYE 1", "NORAD_CAT_ID": 33331, "MEAN_MOTION": 14.64773089, "ECCENTRICITY": 0.0003706, "INCLINATION": 98.12, "RA_OF_ASC_NODE": 148.0546, "ARG_OF_PERICENTER": 16.4564, "MEAN_ANOMALY": 343.6759, "BSTAR": 0.00011921, "EPOCH": "2026-03-13T22:07:31"}, {"OBJECT_NAME": "LUCH DEB", "NORAD_CAT_ID": 44582, "MEAN_MOTION": 1.00701065, "ECCENTRICITY": 0.0017009, "INCLINATION": 14.6048, "RA_OF_ASC_NODE": 354.7817, "ARG_OF_PERICENTER": 87.9758, "MEAN_ANOMALY": 77.8273, "BSTAR": 0.0, "EPOCH": "2026-03-12T17:12:42"}, {"OBJECT_NAME": "LUCH-5X (OLYMP-K 2)", "NORAD_CAT_ID": 55841, "MEAN_MOTION": 1.00270407, "ECCENTRICITY": 0.0001458, "INCLINATION": 0.0279, "RA_OF_ASC_NODE": 89.0645, "ARG_OF_PERICENTER": 119.8966, "MEAN_ANOMALY": 233.8673, "BSTAR": 0.0, "EPOCH": "2026-03-13T13:58:37"}, {"OBJECT_NAME": "LUCH (OLYMP-K 1) DEB", "NORAD_CAT_ID": 67745, "MEAN_MOTION": 0.97993456, "ECCENTRICITY": 0.0520769, "INCLINATION": 1.5795, "RA_OF_ASC_NODE": 85.6956, "ARG_OF_PERICENTER": 329.0115, "MEAN_ANOMALY": 28.4425, "BSTAR": 0.0, "EPOCH": "2026-02-26T11:11:16"}, {"OBJECT_NAME": "LUCH", "NORAD_CAT_ID": 23426, "MEAN_MOTION": 1.00183208, "ECCENTRICITY": 0.0004728, "INCLINATION": 14.7546, "RA_OF_ASC_NODE": 355.344, "ARG_OF_PERICENTER": 224.699, "MEAN_ANOMALY": 135.2716, "BSTAR": 0.0, "EPOCH": "2026-03-12T16:39:38"}, {"OBJECT_NAME": "LUCH-1", "NORAD_CAT_ID": 23680, "MEAN_MOTION": 1.00266907, "ECCENTRICITY": 0.0004384, "INCLINATION": 15.0217, "RA_OF_ASC_NODE": 0.003, "ARG_OF_PERICENTER": 147.6136, "MEAN_ANOMALY": 13.5386, "BSTAR": 0.0, "EPOCH": "2026-03-13T18:16:08"}, {"OBJECT_NAME": "LUCH 5A (SDCM/PRN 140)", "NORAD_CAT_ID": 37951, "MEAN_MOTION": 1.00268953, "ECCENTRICITY": 0.0003411, "INCLINATION": 8.5104, "RA_OF_ASC_NODE": 75.2044, "ARG_OF_PERICENTER": 262.4684, "MEAN_ANOMALY": 295.0348, "BSTAR": 0.0, "EPOCH": "2026-03-13T19:36:38"}, {"OBJECT_NAME": "LUCH 5B (SDCM/PRN 125)", "NORAD_CAT_ID": 38977, "MEAN_MOTION": 1.00271953, "ECCENTRICITY": 0.0003244, "INCLINATION": 10.2781, "RA_OF_ASC_NODE": 50.8078, "ARG_OF_PERICENTER": 227.3464, "MEAN_ANOMALY": 230.5377, "BSTAR": 0.0, "EPOCH": "2026-03-13T23:33:37"}, {"OBJECT_NAME": "LUCH 5V (SDCM/PRN 141)", "NORAD_CAT_ID": 39727, "MEAN_MOTION": 1.00269069, "ECCENTRICITY": 0.000314, "INCLINATION": 4.8975, "RA_OF_ASC_NODE": 70.6733, "ARG_OF_PERICENTER": 297.1295, "MEAN_ANOMALY": 245.4574, "BSTAR": 0.0, "EPOCH": "2026-03-13T23:07:57"}, {"OBJECT_NAME": "LUCH (OLYMP-K 1)", "NORAD_CAT_ID": 40258, "MEAN_MOTION": 0.99116915, "ECCENTRICITY": 0.0003121, "INCLINATION": 1.4978, "RA_OF_ASC_NODE": 84.5508, "ARG_OF_PERICENTER": 187.5711, "MEAN_ANOMALY": 175.9774, "BSTAR": 0.0, "EPOCH": "2026-01-14T19:27:12"}, {"OBJECT_NAME": "TANDEM-X", "NORAD_CAT_ID": 36605, "MEAN_MOTION": 15.19145167, "ECCENTRICITY": 0.0001909, "INCLINATION": 97.4475, "RA_OF_ASC_NODE": 81.6192, "ARG_OF_PERICENTER": 101.4604, "MEAN_ANOMALY": 258.6845, "BSTAR": 8.3268e-05, "EPOCH": "2026-03-13T13:13:24"}, {"OBJECT_NAME": "PAZ", "NORAD_CAT_ID": 43215, "MEAN_MOTION": 15.19158174, "ECCENTRICITY": 0.0001722, "INCLINATION": 97.4462, "RA_OF_ASC_NODE": 81.7323, "ARG_OF_PERICENTER": 88.5098, "MEAN_ANOMALY": 271.6334, "BSTAR": 0.00010771, "EPOCH": "2026-03-13T23:50:12"}, {"OBJECT_NAME": "KONDOR-FKA NO. 1", "NORAD_CAT_ID": 56756, "MEAN_MOTION": 15.19753823, "ECCENTRICITY": 0.0001625, "INCLINATION": 97.44, "RA_OF_ASC_NODE": 268.8789, "ARG_OF_PERICENTER": 82.9203, "MEAN_ANOMALY": 277.2216, "BSTAR": 0.00027241, "EPOCH": "2026-03-13T22:39:44"}, {"OBJECT_NAME": "KONDOR-FKA NO. 2", "NORAD_CAT_ID": 62138, "MEAN_MOTION": 15.19712795, "ECCENTRICITY": 0.0001697, "INCLINATION": 97.4351, "RA_OF_ASC_NODE": 277.7975, "ARG_OF_PERICENTER": 86.2286, "MEAN_ANOMALY": 273.9143, "BSTAR": 0.00012670000000000002, "EPOCH": "2026-03-13T23:15:24"}, {"OBJECT_NAME": "BEIDOU-2 M4 (C12)", "NORAD_CAT_ID": 38251, "MEAN_MOTION": 1.86229915, "ECCENTRICITY": 0.0012191, "INCLINATION": 55.7402, "RA_OF_ASC_NODE": 307.3399, "ARG_OF_PERICENTER": 287.4004, "MEAN_ANOMALY": 72.522, "BSTAR": 0.0, "EPOCH": "2026-03-13T00:07:52"}, {"OBJECT_NAME": "BEIDOU-2 M1", "NORAD_CAT_ID": 31115, "MEAN_MOTION": 1.77349392, "ECCENTRICITY": 0.0002326, "INCLINATION": 50.9679, "RA_OF_ASC_NODE": 222.5681, "ARG_OF_PERICENTER": 33.8688, "MEAN_ANOMALY": 326.1041, "BSTAR": 0.0, "EPOCH": "2026-03-10T03:28:02"}, {"OBJECT_NAME": "BEIDOU-3 M24 (C46)", "NORAD_CAT_ID": 44542, "MEAN_MOTION": 1.86229082, "ECCENTRICITY": 0.0008561, "INCLINATION": 54.3985, "RA_OF_ASC_NODE": 185.9849, "ARG_OF_PERICENTER": 19.8304, "MEAN_ANOMALY": 340.1884, "BSTAR": 0.0, "EPOCH": "2026-03-12T14:10:15"}, {"OBJECT_NAME": "BEIDOU-3 M23 (C45)", "NORAD_CAT_ID": 44543, "MEAN_MOTION": 1.86227389, "ECCENTRICITY": 0.0004976, "INCLINATION": 54.3975, "RA_OF_ASC_NODE": 185.9688, "ARG_OF_PERICENTER": 10.6705, "MEAN_ANOMALY": 318.8703, "BSTAR": 0.0, "EPOCH": "2026-03-12T03:20:09"}, {"OBJECT_NAME": "BEIDOU-3 IGSO-3 (C40)", "NORAD_CAT_ID": 44709, "MEAN_MOTION": 1.00267242, "ECCENTRICITY": 0.0040728, "INCLINATION": 54.9673, "RA_OF_ASC_NODE": 281.9576, "ARG_OF_PERICENTER": 188.7089, "MEAN_ANOMALY": 171.2538, "BSTAR": 0.0, "EPOCH": "2026-03-10T23:36:11"}, {"OBJECT_NAME": "BEIDOU-3 M5 (C23)", "NORAD_CAT_ID": 43581, "MEAN_MOTION": 1.86228824, "ECCENTRICITY": 0.0002388, "INCLINATION": 54.0877, "RA_OF_ASC_NODE": 185.5927, "ARG_OF_PERICENTER": 304.9134, "MEAN_ANOMALY": 55.0505, "BSTAR": 0.0, "EPOCH": "2026-03-12T10:55:13"}, {"OBJECT_NAME": "BEIDOU-3 M22 (C44)", "NORAD_CAT_ID": 44793, "MEAN_MOTION": 1.86232299, "ECCENTRICITY": 0.0007468, "INCLINATION": 54.0225, "RA_OF_ASC_NODE": 303.2142, "ARG_OF_PERICENTER": 38.0258, "MEAN_ANOMALY": 322.0804, "BSTAR": 0.0, "EPOCH": "2026-03-12T23:11:55"}, {"OBJECT_NAME": "BEIDOU-3 M6 (C24)", "NORAD_CAT_ID": 43582, "MEAN_MOTION": 1.86227825, "ECCENTRICITY": 0.0005988, "INCLINATION": 54.0872, "RA_OF_ASC_NODE": 185.5682, "ARG_OF_PERICENTER": 41.7221, "MEAN_ANOMALY": 318.3092, "BSTAR": 0.0, "EPOCH": "2026-03-12T20:31:06"}, {"OBJECT_NAME": "BEIDOU-3 M21 (C43)", "NORAD_CAT_ID": 44794, "MEAN_MOTION": 1.86227925, "ECCENTRICITY": 0.0005425, "INCLINATION": 53.9966, "RA_OF_ASC_NODE": 303.2101, "ARG_OF_PERICENTER": 33.1471, "MEAN_ANOMALY": 326.9381, "BSTAR": 0.0, "EPOCH": "2026-03-12T00:46:41"}, {"OBJECT_NAME": "BEIDOU-2 G8 (C01)", "NORAD_CAT_ID": 44231, "MEAN_MOTION": 1.00273975, "ECCENTRICITY": 0.0011489, "INCLINATION": 1.4155, "RA_OF_ASC_NODE": 74.2587, "ARG_OF_PERICENTER": 274.6914, "MEAN_ANOMALY": 311.0157, "BSTAR": 0.0, "EPOCH": "2026-03-13T22:55:34"}, {"OBJECT_NAME": "BEIDOU-3 IGSO-2 (C39)", "NORAD_CAT_ID": 44337, "MEAN_MOTION": 1.00247364, "ECCENTRICITY": 0.0038734, "INCLINATION": 55.2338, "RA_OF_ASC_NODE": 159.8353, "ARG_OF_PERICENTER": 206.4752, "MEAN_ANOMALY": 153.7223, "BSTAR": 0.0, "EPOCH": "2026-02-26T16:31:51"}, {"OBJECT_NAME": "BEIDOU-3 M10 (C30)", "NORAD_CAT_ID": 43246, "MEAN_MOTION": 1.86229238, "ECCENTRICITY": 0.0005206, "INCLINATION": 54.2796, "RA_OF_ASC_NODE": 303.4048, "ARG_OF_PERICENTER": 25.3248, "MEAN_ANOMALY": 334.7506, "BSTAR": 0.0, "EPOCH": "2026-03-11T03:46:01"}, {"OBJECT_NAME": "BEIDOU-2 IGSO-7 (C16)", "NORAD_CAT_ID": 43539, "MEAN_MOTION": 1.00280738, "ECCENTRICITY": 0.0100561, "INCLINATION": 55.1863, "RA_OF_ASC_NODE": 163.8949, "ARG_OF_PERICENTER": 236.784, "MEAN_ANOMALY": 122.3454, "BSTAR": 0.0, "EPOCH": "2026-03-13T15:56:01"}, {"OBJECT_NAME": "BEIDOU-2 M6 (C14)", "NORAD_CAT_ID": 38775, "MEAN_MOTION": 1.86231021, "ECCENTRICITY": 0.0014127, "INCLINATION": 56.4609, "RA_OF_ASC_NODE": 66.0825, "ARG_OF_PERICENTER": 342.5009, "MEAN_ANOMALY": 17.4715, "BSTAR": 0.0, "EPOCH": "2026-03-12T17:10:29"}, {"OBJECT_NAME": "CHINASAT 31 (BEIDOU-1 *)", "NORAD_CAT_ID": 26643, "MEAN_MOTION": 0.99256234, "ECCENTRICITY": 0.0077094, "INCLINATION": 12.4543, "RA_OF_ASC_NODE": 28.03, "ARG_OF_PERICENTER": 84.8533, "MEAN_ANOMALY": 88.8595, "BSTAR": 0.0, "EPOCH": "2026-03-13T03:19:44"}, {"OBJECT_NAME": "BEIDOU-2 G6 (C02)", "NORAD_CAT_ID": 38953, "MEAN_MOTION": 1.00276062, "ECCENTRICITY": 0.001054, "INCLINATION": 4.1785, "RA_OF_ASC_NODE": 74.5404, "ARG_OF_PERICENTER": 306.4198, "MEAN_ANOMALY": 188.414, "BSTAR": 0.0, "EPOCH": "2026-03-13T20:55:45"}, {"OBJECT_NAME": "BEIDOU-1 G3", "NORAD_CAT_ID": 27813, "MEAN_MOTION": 0.99765897, "ECCENTRICITY": 0.0019498, "INCLINATION": 11.1948, "RA_OF_ASC_NODE": 42.0288, "ARG_OF_PERICENTER": 301.8279, "MEAN_ANOMALY": 234.54, "BSTAR": 0.0, "EPOCH": "2026-03-13T22:33:51"}, {"OBJECT_NAME": "BEIDOU-3S IGSO-1S (C31)", "NORAD_CAT_ID": 40549, "MEAN_MOTION": 1.00272189, "ECCENTRICITY": 0.0035647, "INCLINATION": 49.3736, "RA_OF_ASC_NODE": 296.6132, "ARG_OF_PERICENTER": 190.1678, "MEAN_ANOMALY": 352.9044, "BSTAR": 0.0, "EPOCH": "2026-03-13T14:08:14"}, {"OBJECT_NAME": "BEIDOU-1 G4", "NORAD_CAT_ID": 30323, "MEAN_MOTION": 0.99158371, "ECCENTRICITY": 0.0057038, "INCLINATION": 9.6698, "RA_OF_ASC_NODE": 57.9536, "ARG_OF_PERICENTER": 271.1825, "MEAN_ANOMALY": 91.8212, "BSTAR": 0.0, "EPOCH": "2026-03-13T18:40:28"}, {"OBJECT_NAME": "BEIDOU-3 M12 (C26)", "NORAD_CAT_ID": 43602, "MEAN_MOTION": 1.8622785, "ECCENTRICITY": 0.0008368, "INCLINATION": 54.1816, "RA_OF_ASC_NODE": 184.3275, "ARG_OF_PERICENTER": 38.978, "MEAN_ANOMALY": 321.0706, "BSTAR": 0.0, "EPOCH": "2026-03-12T06:09:12"}, {"OBJECT_NAME": "SHIJIAN-16 (SJ-16)", "NORAD_CAT_ID": 39358, "MEAN_MOTION": 14.92370565, "ECCENTRICITY": 0.001532, "INCLINATION": 74.9729, "RA_OF_ASC_NODE": 176.9542, "ARG_OF_PERICENTER": 101.4806, "MEAN_ANOMALY": 258.8104, "BSTAR": 0.00032554, "EPOCH": "2026-03-13T23:40:36"}, {"OBJECT_NAME": "SHIJIAN-20 (SJ-20)", "NORAD_CAT_ID": 44910, "MEAN_MOTION": 1.00082407, "ECCENTRICITY": 0.0001536, "INCLINATION": 4.6699, "RA_OF_ASC_NODE": 76.2395, "ARG_OF_PERICENTER": 16.315, "MEAN_ANOMALY": 96.486, "BSTAR": 0.0, "EPOCH": "2026-03-12T20:33:00"}, {"OBJECT_NAME": "SHIJIAN-6 01A (SJ-6 01A)", "NORAD_CAT_ID": 28413, "MEAN_MOTION": 15.16526688, "ECCENTRICITY": 0.0008183, "INCLINATION": 97.5978, "RA_OF_ASC_NODE": 99.7091, "ARG_OF_PERICENTER": 104.1313, "MEAN_ANOMALY": 256.0829, "BSTAR": 0.0005259500000000001, "EPOCH": "2026-03-13T19:17:28"}, {"OBJECT_NAME": "SHIJIAN-6 02B (SJ-6 02B)", "NORAD_CAT_ID": 29506, "MEAN_MOTION": 15.01021872, "ECCENTRICITY": 0.0013821, "INCLINATION": 97.7077, "RA_OF_ASC_NODE": 102.6645, "ARG_OF_PERICENTER": 30.0857, "MEAN_ANOMALY": 330.1158, "BSTAR": 0.00018838, "EPOCH": "2026-03-13T23:08:48"}, {"OBJECT_NAME": "SHIJIAN-30A (SJ-30A)", "NORAD_CAT_ID": 66545, "MEAN_MOTION": 15.15423779, "ECCENTRICITY": 0.0011472, "INCLINATION": 51.7981, "RA_OF_ASC_NODE": 265.5259, "ARG_OF_PERICENTER": 306.6475, "MEAN_ANOMALY": 53.3446, "BSTAR": 0.0005244900000000001, "EPOCH": "2026-03-13T22:48:09"}, {"OBJECT_NAME": "SHIJIAN-6 03A (SJ-6 03A)", "NORAD_CAT_ID": 33408, "MEAN_MOTION": 15.16124436, "ECCENTRICITY": 0.0011042, "INCLINATION": 97.8533, "RA_OF_ASC_NODE": 103.0077, "ARG_OF_PERICENTER": 348.3714, "MEAN_ANOMALY": 11.726, "BSTAR": 0.00021966, "EPOCH": "2026-03-13T23:28:43"}, {"OBJECT_NAME": "SHIJIAN-6 04B (SJ-6 04B)", "NORAD_CAT_ID": 37180, "MEAN_MOTION": 14.99126331, "ECCENTRICITY": 0.0009055, "INCLINATION": 97.8747, "RA_OF_ASC_NODE": 77.415, "ARG_OF_PERICENTER": 277.7452, "MEAN_ANOMALY": 82.2742, "BSTAR": 4.071e-05, "EPOCH": "2026-03-13T23:33:25"}, {"OBJECT_NAME": "SHIJIAN-6 02A (SJ-6 02A)", "NORAD_CAT_ID": 29505, "MEAN_MOTION": 15.15768295, "ECCENTRICITY": 0.0004763, "INCLINATION": 97.6496, "RA_OF_ASC_NODE": 113.376, "ARG_OF_PERICENTER": 104.7518, "MEAN_ANOMALY": 255.4243, "BSTAR": 0.00032697, "EPOCH": "2026-03-14T00:03:32"}, {"OBJECT_NAME": "SHIJIAN-6 03B (SJ-6 03B)", "NORAD_CAT_ID": 33409, "MEAN_MOTION": 15.03909215, "ECCENTRICITY": 0.0019698, "INCLINATION": 97.8671, "RA_OF_ASC_NODE": 91.2719, "ARG_OF_PERICENTER": 8.8097, "MEAN_ANOMALY": 351.347, "BSTAR": 0.00026502, "EPOCH": "2026-03-13T23:16:39"}, {"OBJECT_NAME": "SHIJIAN-6 04A (SJ-6 04A)", "NORAD_CAT_ID": 37179, "MEAN_MOTION": 15.1671358, "ECCENTRICITY": 0.0018691, "INCLINATION": 97.8382, "RA_OF_ASC_NODE": 92.9623, "ARG_OF_PERICENTER": 189.0595, "MEAN_ANOMALY": 171.0302, "BSTAR": 0.00034501, "EPOCH": "2026-03-13T23:58:57"}, {"OBJECT_NAME": "SHIJIAN-17 (SJ-17)", "NORAD_CAT_ID": 41838, "MEAN_MOTION": 0.99865501, "ECCENTRICITY": 0.0001148, "INCLINATION": 5.5064, "RA_OF_ASC_NODE": 73.7601, "ARG_OF_PERICENTER": 325.6027, "MEAN_ANOMALY": 47.6368, "BSTAR": 0.0, "EPOCH": "2026-03-12T17:13:52"}, {"OBJECT_NAME": "SHIJIAN-21 (SJ-21)", "NORAD_CAT_ID": 49330, "MEAN_MOTION": 1.00263511, "ECCENTRICITY": 0.0048014, "INCLINATION": 4.8865, "RA_OF_ASC_NODE": 61.7086, "ARG_OF_PERICENTER": 171.424, "MEAN_ANOMALY": 61.5631, "BSTAR": 0.0, "EPOCH": "2026-03-13T23:41:25"}, {"OBJECT_NAME": "SHIJIAN-23 (SJ-23)", "NORAD_CAT_ID": 55131, "MEAN_MOTION": 1.00484158, "ECCENTRICITY": 0.0005724, "INCLINATION": 3.4708, "RA_OF_ASC_NODE": 79.5278, "ARG_OF_PERICENTER": 265.1652, "MEAN_ANOMALY": 240.6077, "BSTAR": 0.0, "EPOCH": "2026-03-13T18:28:41"}, {"OBJECT_NAME": "SHIJIAN-19 (SJ-19)", "NORAD_CAT_ID": 61444, "MEAN_MOTION": 15.77608314, "ECCENTRICITY": 0.0006944, "INCLINATION": 41.601, "RA_OF_ASC_NODE": 76.8644, "ARG_OF_PERICENTER": 34.8351, "MEAN_ANOMALY": 325.295, "BSTAR": 9.0833e-05, "EPOCH": "2024-10-10T17:00:10"}, {"OBJECT_NAME": "SHIJIAN-6 01B (SJ-6 01B)", "NORAD_CAT_ID": 28414, "MEAN_MOTION": 15.05666414, "ECCENTRICITY": 0.0006787, "INCLINATION": 97.6147, "RA_OF_ASC_NODE": 92.0716, "ARG_OF_PERICENTER": 101.7171, "MEAN_ANOMALY": 258.4817, "BSTAR": 0.00011612, "EPOCH": "2026-03-13T23:18:12"}, {"OBJECT_NAME": "SHIJIAN-25 (SJ-25)", "NORAD_CAT_ID": 62485, "MEAN_MOTION": 1.0027194, "ECCENTRICITY": 0.0048627, "INCLINATION": 4.8863, "RA_OF_ASC_NODE": 61.7143, "ARG_OF_PERICENTER": 166.3864, "MEAN_ANOMALY": 329.1967, "BSTAR": 0.0, "EPOCH": "2026-03-13T17:14:33"}, {"OBJECT_NAME": "SHIJIAN-26 (SJ-26)", "NORAD_CAT_ID": 64199, "MEAN_MOTION": 15.22615444, "ECCENTRICITY": 0.0018329, "INCLINATION": 97.4607, "RA_OF_ASC_NODE": 152.108, "ARG_OF_PERICENTER": 330.5834, "MEAN_ANOMALY": 29.4369, "BSTAR": 0.00030253, "EPOCH": "2026-03-13T22:31:08"}, {"OBJECT_NAME": "SHIJIAN-30B (SJ-30B)", "NORAD_CAT_ID": 66546, "MEAN_MOTION": 15.15360631, "ECCENTRICITY": 0.0009402, "INCLINATION": 51.7965, "RA_OF_ASC_NODE": 265.5138, "ARG_OF_PERICENTER": 308.952, "MEAN_ANOMALY": 51.0618, "BSTAR": 0.00055464, "EPOCH": "2026-03-13T22:49:39"}, {"OBJECT_NAME": "SHIJIAN-30C (SJ-30C)", "NORAD_CAT_ID": 66547, "MEAN_MOTION": 15.15463214, "ECCENTRICITY": 0.0010197, "INCLINATION": 51.7973, "RA_OF_ASC_NODE": 265.5296, "ARG_OF_PERICENTER": 299.7369, "MEAN_ANOMALY": 60.2592, "BSTAR": 0.0005682199999999999, "EPOCH": "2026-03-13T22:50:54"}, {"OBJECT_NAME": "SHIJIAN-28 (SJ-28)", "NORAD_CAT_ID": 66549, "MEAN_MOTION": 1.00269894, "ECCENTRICITY": 6.05e-05, "INCLINATION": 4.7853, "RA_OF_ASC_NODE": 273.572, "ARG_OF_PERICENTER": 175.7995, "MEAN_ANOMALY": 180.8826, "BSTAR": 0.0, "EPOCH": "2026-03-13T22:47:42"}, {"OBJECT_NAME": "GSAT0101 (GALILEO-PFM)", "NORAD_CAT_ID": 37846, "MEAN_MOTION": 1.70475478, "ECCENTRICITY": 0.0003975, "INCLINATION": 57.0318, "RA_OF_ASC_NODE": 344.8758, "ARG_OF_PERICENTER": 357.0591, "MEAN_ANOMALY": 2.9533, "BSTAR": 0.0, "EPOCH": "2026-02-22T11:08:37"}, {"OBJECT_NAME": "GSAT0219 (GALILEO 23)", "NORAD_CAT_ID": 43566, "MEAN_MOTION": 1.70474822, "ECCENTRICITY": 0.0004318, "INCLINATION": 57.205, "RA_OF_ASC_NODE": 344.5202, "ARG_OF_PERICENTER": 344.0327, "MEAN_ANOMALY": 15.9782, "BSTAR": 0.0, "EPOCH": "2026-03-08T00:37:58"}, {"OBJECT_NAME": "GSAT0207 (GALILEO 15)", "NORAD_CAT_ID": 41859, "MEAN_MOTION": 1.70474457, "ECCENTRICITY": 0.0005361, "INCLINATION": 55.4358, "RA_OF_ASC_NODE": 103.7267, "ARG_OF_PERICENTER": 309.9075, "MEAN_ANOMALY": 50.1195, "BSTAR": 0.0, "EPOCH": "2026-03-13T17:15:10"}, {"OBJECT_NAME": "GSAT0103 (GALILEO-FM3)", "NORAD_CAT_ID": 38857, "MEAN_MOTION": 1.70473527, "ECCENTRICITY": 0.000557, "INCLINATION": 55.7441, "RA_OF_ASC_NODE": 104.2408, "ARG_OF_PERICENTER": 286.1218, "MEAN_ANOMALY": 73.8831, "BSTAR": 0.0, "EPOCH": "2026-03-10T22:17:59"}, {"OBJECT_NAME": "GSAT0232 (GALILEO 32)", "NORAD_CAT_ID": 61182, "MEAN_MOTION": 1.70443939, "ECCENTRICITY": 0.00036, "INCLINATION": 55.2225, "RA_OF_ASC_NODE": 224.5881, "ARG_OF_PERICENTER": 296.6314, "MEAN_ANOMALY": 116.1306, "BSTAR": 0.0, "EPOCH": "2026-02-17T15:52:34"}, {"OBJECT_NAME": "GSAT0226 (GALILEO 31)", "NORAD_CAT_ID": 61183, "MEAN_MOTION": 1.70474359, "ECCENTRICITY": 0.0001584, "INCLINATION": 55.2155, "RA_OF_ASC_NODE": 223.9355, "ARG_OF_PERICENTER": 137.4612, "MEAN_ANOMALY": 46.3182, "BSTAR": 0.0, "EPOCH": "2026-03-13T18:37:21"}, {"OBJECT_NAME": "GSAT0212 (GALILEO 16)", "NORAD_CAT_ID": 41860, "MEAN_MOTION": 1.70474723, "ECCENTRICITY": 0.0003884, "INCLINATION": 55.4332, "RA_OF_ASC_NODE": 103.7422, "ARG_OF_PERICENTER": 334.9903, "MEAN_ANOMALY": 25.0622, "BSTAR": 0.0, "EPOCH": "2026-03-12T23:39:35"}, {"OBJECT_NAME": "GSAT0233 (GALILEO 33)", "NORAD_CAT_ID": 67160, "MEAN_MOTION": 1.70474578, "ECCENTRICITY": 0.0003011, "INCLINATION": 54.3935, "RA_OF_ASC_NODE": 105.2952, "ARG_OF_PERICENTER": 207.0582, "MEAN_ANOMALY": 359.4109, "BSTAR": 0.0, "EPOCH": "2026-02-13T12:00:00"}, {"OBJECT_NAME": "GSAT0213 (GALILEO 17)", "NORAD_CAT_ID": 41861, "MEAN_MOTION": 1.70475014, "ECCENTRICITY": 0.0005437, "INCLINATION": 55.4354, "RA_OF_ASC_NODE": 103.7885, "ARG_OF_PERICENTER": 293.5263, "MEAN_ANOMALY": 66.4835, "BSTAR": 0.0, "EPOCH": "2026-03-11T14:14:38"}, {"OBJECT_NAME": "GSAT0234 (GALILEO 34)", "NORAD_CAT_ID": 67162, "MEAN_MOTION": 1.70475046, "ECCENTRICITY": 0.0002786, "INCLINATION": 54.2701, "RA_OF_ASC_NODE": 104.8613, "ARG_OF_PERICENTER": 225.0665, "MEAN_ANOMALY": 135.9201, "BSTAR": 0.0, "EPOCH": "2026-03-13T07:42:19"}, {"OBJECT_NAME": "GSAT0214 (GALILEO 18)", "NORAD_CAT_ID": 41862, "MEAN_MOTION": 1.70474834, "ECCENTRICITY": 0.0004476, "INCLINATION": 55.4337, "RA_OF_ASC_NODE": 103.7448, "ARG_OF_PERICENTER": 297.9628, "MEAN_ANOMALY": 62.0628, "BSTAR": 0.0, "EPOCH": "2026-03-12T21:54:20"}, {"OBJECT_NAME": "GSAT0102 (GALILEO-FM2)", "NORAD_CAT_ID": 37847, "MEAN_MOTION": 1.70475778, "ECCENTRICITY": 0.0005422, "INCLINATION": 57.0301, "RA_OF_ASC_NODE": 344.6971, "ARG_OF_PERICENTER": 341.2092, "MEAN_ANOMALY": 154.1953, "BSTAR": 0.0, "EPOCH": "2026-03-01T01:30:59"}, {"OBJECT_NAME": "GSAT0215 (GALILEO 19)", "NORAD_CAT_ID": 43055, "MEAN_MOTION": 1.70474604, "ECCENTRICITY": 5.03e-05, "INCLINATION": 55.1052, "RA_OF_ASC_NODE": 224.1555, "ARG_OF_PERICENTER": 355.2258, "MEAN_ANOMALY": 4.7321, "BSTAR": 0.0, "EPOCH": "2026-03-12T19:35:18"}, {"OBJECT_NAME": "GSAT0216 (GALILEO 20)", "NORAD_CAT_ID": 43056, "MEAN_MOTION": 1.70474728, "ECCENTRICITY": 0.0001729, "INCLINATION": 55.1057, "RA_OF_ASC_NODE": 224.1638, "ARG_OF_PERICENTER": 313.2085, "MEAN_ANOMALY": 46.7359, "BSTAR": 0.0, "EPOCH": "2026-03-12T12:29:59"}, {"OBJECT_NAME": "GALILEO104 [GAL]", "NORAD_CAT_ID": 38858, "MEAN_MOTION": 1.64592169, "ECCENTRICITY": 0.0001481, "INCLINATION": 55.4156, "RA_OF_ASC_NODE": 121.7581, "ARG_OF_PERICENTER": 313.3657, "MEAN_ANOMALY": 182.5612, "BSTAR": 0.0, "EPOCH": "2024-06-18T00:14:41"}, {"OBJECT_NAME": "GSAT0201 (GALILEO 5)", "NORAD_CAT_ID": 40128, "MEAN_MOTION": 1.8552017, "ECCENTRICITY": 0.1658807, "INCLINATION": 48.9815, "RA_OF_ASC_NODE": 277.4406, "ARG_OF_PERICENTER": 175.5932, "MEAN_ANOMALY": 186.0859, "BSTAR": 0.0, "EPOCH": "2026-03-11T07:43:01"}, {"OBJECT_NAME": "GSAT0217 (GALILEO 21)", "NORAD_CAT_ID": 43057, "MEAN_MOTION": 1.70474639, "ECCENTRICITY": 0.0001948, "INCLINATION": 55.1048, "RA_OF_ASC_NODE": 224.1555, "ARG_OF_PERICENTER": 350.8522, "MEAN_ANOMALY": 9.1027, "BSTAR": 0.0, "EPOCH": "2026-03-12T17:47:52"}, {"OBJECT_NAME": "GSAT0202 (GALILEO 6)", "NORAD_CAT_ID": 40129, "MEAN_MOTION": 1.85520847, "ECCENTRICITY": 0.1659654, "INCLINATION": 48.9971, "RA_OF_ASC_NODE": 276.5149, "ARG_OF_PERICENTER": 176.3418, "MEAN_ANOMALY": 185.0558, "BSTAR": 0.0, "EPOCH": "2026-03-11T13:51:31"}, {"OBJECT_NAME": "GSAT0218 (GALILEO 22)", "NORAD_CAT_ID": 43058, "MEAN_MOTION": 1.70474604, "ECCENTRICITY": 0.0002024, "INCLINATION": 55.1035, "RA_OF_ASC_NODE": 224.1311, "ARG_OF_PERICENTER": 298.9535, "MEAN_ANOMALY": 60.9828, "BSTAR": 0.0, "EPOCH": "2026-03-13T13:09:25"}, {"OBJECT_NAME": "GSAT0203 (GALILEO 7)", "NORAD_CAT_ID": 40544, "MEAN_MOTION": 1.70475763, "ECCENTRICITY": 0.0004663, "INCLINATION": 56.8181, "RA_OF_ASC_NODE": 344.2043, "ARG_OF_PERICENTER": 298.714, "MEAN_ANOMALY": 61.2673, "BSTAR": 0.0, "EPOCH": "2026-03-13T14:23:31"}, {"OBJECT_NAME": "BEIDOU-2 IGSO-1 (C06)", "NORAD_CAT_ID": 36828, "MEAN_MOTION": 1.00250201, "ECCENTRICITY": 0.0054469, "INCLINATION": 54.2923, "RA_OF_ASC_NODE": 163.8253, "ARG_OF_PERICENTER": 219.3556, "MEAN_ANOMALY": 215.6821, "BSTAR": 0.0, "EPOCH": "2026-03-13T21:32:09"}, {"OBJECT_NAME": "BEIDOU-2 IGSO-2 (C07)", "NORAD_CAT_ID": 37256, "MEAN_MOTION": 1.00257833, "ECCENTRICITY": 0.004749, "INCLINATION": 47.7215, "RA_OF_ASC_NODE": 273.0501, "ARG_OF_PERICENTER": 213.2827, "MEAN_ANOMALY": 326.5355, "BSTAR": 0.0, "EPOCH": "2026-03-10T11:51:55"}, {"OBJECT_NAME": "BEIDOU-2 IGSO-3 (C08)", "NORAD_CAT_ID": 37384, "MEAN_MOTION": 1.00293315, "ECCENTRICITY": 0.0035062, "INCLINATION": 62.2726, "RA_OF_ASC_NODE": 41.1265, "ARG_OF_PERICENTER": 190.7769, "MEAN_ANOMALY": 297.326, "BSTAR": 0.0, "EPOCH": "2026-03-05T17:18:14"}, {"OBJECT_NAME": "BEIDOU-2 IGSO-4 (C09)", "NORAD_CAT_ID": 37763, "MEAN_MOTION": 1.00264423, "ECCENTRICITY": 0.0155085, "INCLINATION": 54.5894, "RA_OF_ASC_NODE": 166.5549, "ARG_OF_PERICENTER": 231.062, "MEAN_ANOMALY": 149.1617, "BSTAR": 0.0, "EPOCH": "2026-03-11T18:52:33"}, {"OBJECT_NAME": "BEIDOU-2 IGSO-5 (C10)", "NORAD_CAT_ID": 37948, "MEAN_MOTION": 1.00270695, "ECCENTRICITY": 0.0108864, "INCLINATION": 47.8524, "RA_OF_ASC_NODE": 272.7266, "ARG_OF_PERICENTER": 221.072, "MEAN_ANOMALY": 318.7247, "BSTAR": 0.0, "EPOCH": "2026-03-13T12:25:15"}, {"OBJECT_NAME": "BEIDOU-3S IGSO-2S (C56)", "NORAD_CAT_ID": 40938, "MEAN_MOTION": 1.00254296, "ECCENTRICITY": 0.0061515, "INCLINATION": 49.4373, "RA_OF_ASC_NODE": 260.4556, "ARG_OF_PERICENTER": 187.1638, "MEAN_ANOMALY": 17.4903, "BSTAR": 0.0, "EPOCH": "2026-01-27T16:14:57"}, {"OBJECT_NAME": "BEIDOU-2 IGSO-6 (C13)", "NORAD_CAT_ID": 41434, "MEAN_MOTION": 1.00277411, "ECCENTRICITY": 0.0059566, "INCLINATION": 60.0969, "RA_OF_ASC_NODE": 39.005, "ARG_OF_PERICENTER": 233.2714, "MEAN_ANOMALY": 308.7278, "BSTAR": 0.0, "EPOCH": "2026-03-11T21:02:52"}, {"OBJECT_NAME": "BEIDOU-3 IGSO-1 (C38)", "NORAD_CAT_ID": 44204, "MEAN_MOTION": 1.00268377, "ECCENTRICITY": 0.0025635, "INCLINATION": 58.5672, "RA_OF_ASC_NODE": 38.6298, "ARG_OF_PERICENTER": 236.0438, "MEAN_ANOMALY": 335.2844, "BSTAR": 0.0, "EPOCH": "2026-03-13T21:18:00"}, {"OBJECT_NAME": "COSMO-SKYMED 1", "NORAD_CAT_ID": 31598, "MEAN_MOTION": 14.96574619, "ECCENTRICITY": 0.0001578, "INCLINATION": 97.8882, "RA_OF_ASC_NODE": 264.0096, "ARG_OF_PERICENTER": 95.4766, "MEAN_ANOMALY": 264.6635, "BSTAR": 0.00042908000000000003, "EPOCH": "2026-03-13T22:38:48"}, {"OBJECT_NAME": "COSMO-SKYMED 2", "NORAD_CAT_ID": 32376, "MEAN_MOTION": 14.8214924, "ECCENTRICITY": 0.0001327, "INCLINATION": 97.8868, "RA_OF_ASC_NODE": 257.9453, "ARG_OF_PERICENTER": 83.9144, "MEAN_ANOMALY": 276.2221, "BSTAR": 8.912600000000001e-05, "EPOCH": "2026-03-13T23:18:30"}, {"OBJECT_NAME": "COSMO-SKYMED 4", "NORAD_CAT_ID": 37216, "MEAN_MOTION": 14.82144204, "ECCENTRICITY": 0.0001495, "INCLINATION": 97.8871, "RA_OF_ASC_NODE": 257.9577, "ARG_OF_PERICENTER": 83.0447, "MEAN_ANOMALY": 277.0936, "BSTAR": 6.1181e-05, "EPOCH": "2026-03-13T23:36:43"}, {"OBJECT_NAME": "COSMO-SKYMED 3", "NORAD_CAT_ID": 33412, "MEAN_MOTION": 15.06287447, "ECCENTRICITY": 0.0014664, "INCLINATION": 97.8416, "RA_OF_ASC_NODE": 289.9339, "ARG_OF_PERICENTER": 225.8003, "MEAN_ANOMALY": 134.202, "BSTAR": 0.00029846, "EPOCH": "2026-03-13T23:18:31"}, {"OBJECT_NAME": "NAVSTAR 66 (USA 232)", "NORAD_CAT_ID": 37753, "MEAN_MOTION": 2.00563331, "ECCENTRICITY": 0.0140225, "INCLINATION": 56.6074, "RA_OF_ASC_NODE": 335.748, "ARG_OF_PERICENTER": 60.959, "MEAN_ANOMALY": 141.4014, "BSTAR": 0.0, "EPOCH": "2026-03-13T10:01:31"}, {"OBJECT_NAME": "NAVSTAR 46 (USA 145)", "NORAD_CAT_ID": 25933, "MEAN_MOTION": 2.00567343, "ECCENTRICITY": 0.0106389, "INCLINATION": 51.5489, "RA_OF_ASC_NODE": 299.64, "ARG_OF_PERICENTER": 171.929, "MEAN_ANOMALY": 9.148, "BSTAR": 0.0, "EPOCH": "2026-03-13T19:41:18"}, {"OBJECT_NAME": "NAVSTAR 49 (USA 154)", "NORAD_CAT_ID": 26605, "MEAN_MOTION": 2.00570193, "ECCENTRICITY": 0.0173455, "INCLINATION": 55.5687, "RA_OF_ASC_NODE": 98.7251, "ARG_OF_PERICENTER": 265.6826, "MEAN_ANOMALY": 103.4412, "BSTAR": 0.0, "EPOCH": "2026-03-13T16:25:19"}, {"OBJECT_NAME": "NAVSTAR 52 (USA 168)", "NORAD_CAT_ID": 27704, "MEAN_MOTION": 1.94743161, "ECCENTRICITY": 0.0004627, "INCLINATION": 54.8698, "RA_OF_ASC_NODE": 328.8449, "ARG_OF_PERICENTER": 343.01, "MEAN_ANOMALY": 204.2637, "BSTAR": 0.0, "EPOCH": "2026-03-11T13:01:38"}, {"OBJECT_NAME": "NAVSTAR 53 (USA 175)", "NORAD_CAT_ID": 28129, "MEAN_MOTION": 1.92678601, "ECCENTRICITY": 0.000316, "INCLINATION": 54.9721, "RA_OF_ASC_NODE": 26.8461, "ARG_OF_PERICENTER": 314.5189, "MEAN_ANOMALY": 45.4493, "BSTAR": 0.0, "EPOCH": "2026-03-12T12:24:25"}, {"OBJECT_NAME": "NAVSTAR 55 (USA 178)", "NORAD_CAT_ID": 28361, "MEAN_MOTION": 2.00552384, "ECCENTRICITY": 0.0159871, "INCLINATION": 54.7964, "RA_OF_ASC_NODE": 90.5792, "ARG_OF_PERICENTER": 298.9108, "MEAN_ANOMALY": 53.8796, "BSTAR": 0.0, "EPOCH": "2026-03-13T09:35:38"}, {"OBJECT_NAME": "NAVSTAR 63 (USA 203)", "NORAD_CAT_ID": 34661, "MEAN_MOTION": 2.00555628, "ECCENTRICITY": 0.0144936, "INCLINATION": 54.5029, "RA_OF_ASC_NODE": 214.4867, "ARG_OF_PERICENTER": 61.4833, "MEAN_ANOMALY": 120.7701, "BSTAR": 0.0, "EPOCH": "2026-03-13T13:47:46"}, {"OBJECT_NAME": "DMSP 5D-3 F18 (USA 210)", "NORAD_CAT_ID": 35951, "MEAN_MOTION": 14.14838953, "ECCENTRICITY": 0.0011368, "INCLINATION": 98.8968, "RA_OF_ASC_NODE": 53.9706, "ARG_OF_PERICENTER": 156.3337, "MEAN_ANOMALY": 203.8361, "BSTAR": 0.00018149000000000003, "EPOCH": "2026-03-13T22:55:56"}, {"OBJECT_NAME": "AEHF-1 (USA 214)", "NORAD_CAT_ID": 36868, "MEAN_MOTION": 1.00269989, "ECCENTRICITY": 0.0004323, "INCLINATION": 7.9828, "RA_OF_ASC_NODE": 69.2901, "ARG_OF_PERICENTER": 282.4183, "MEAN_ANOMALY": 82.5563, "BSTAR": 0.0, "EPOCH": "2026-03-13T15:32:11"}, {"OBJECT_NAME": "AEHF-2 (USA 235)", "NORAD_CAT_ID": 38254, "MEAN_MOTION": 1.0027274, "ECCENTRICITY": 0.0003126, "INCLINATION": 6.4295, "RA_OF_ASC_NODE": 58.1783, "ARG_OF_PERICENTER": 283.2868, "MEAN_ANOMALY": 94.5435, "BSTAR": 0.0, "EPOCH": "2026-03-13T18:44:20"}, {"OBJECT_NAME": "AEHF-5 (USA 292)", "NORAD_CAT_ID": 44481, "MEAN_MOTION": 1.00269143, "ECCENTRICITY": 0.0071181, "INCLINATION": 1.5525, "RA_OF_ASC_NODE": 329.312, "ARG_OF_PERICENTER": 3.3698, "MEAN_ANOMALY": 272.1078, "BSTAR": 0.0, "EPOCH": "2026-03-13T22:40:43"}, {"OBJECT_NAME": "AEHF-4 (USA 288)", "NORAD_CAT_ID": 43651, "MEAN_MOTION": 1.00270052, "ECCENTRICITY": 0.0063991, "INCLINATION": 1.422, "RA_OF_ASC_NODE": 355.4529, "ARG_OF_PERICENTER": 359.1371, "MEAN_ANOMALY": 78.2689, "BSTAR": 0.0, "EPOCH": "2026-03-13T21:55:24"}, {"OBJECT_NAME": "WGS F7 (USA 263)", "NORAD_CAT_ID": 40746, "MEAN_MOTION": 1.00272244, "ECCENTRICITY": 2.25e-05, "INCLINATION": 0.0131, "RA_OF_ASC_NODE": 135.051, "ARG_OF_PERICENTER": 270.5458, "MEAN_ANOMALY": 158.3684, "BSTAR": 0.0, "EPOCH": "2026-03-13T14:30:54"}, {"OBJECT_NAME": "SBSS (USA 216)", "NORAD_CAT_ID": 37168, "MEAN_MOTION": 15.15755191, "ECCENTRICITY": 0.0082509, "INCLINATION": 97.7475, "RA_OF_ASC_NODE": 315.5523, "ARG_OF_PERICENTER": 174.1816, "MEAN_ANOMALY": 311.3892, "BSTAR": 0.00025053, "EPOCH": "2026-03-12T23:42:37"}, {"OBJECT_NAME": "USA 81", "NORAD_CAT_ID": 21949, "MEAN_MOTION": 14.32369362, "ECCENTRICITY": 0.0002353, "INCLINATION": 85.0076, "RA_OF_ASC_NODE": 129.041, "ARG_OF_PERICENTER": 74.3719, "MEAN_ANOMALY": 285.7733, "BSTAR": 5.7183e-05, "EPOCH": "2026-03-13T20:24:23"}, {"OBJECT_NAME": "NUSAT-8 (MARIE)", "NORAD_CAT_ID": 45018, "MEAN_MOTION": 16.42177442, "ECCENTRICITY": 0.0011737, "INCLINATION": 97.1425, "RA_OF_ASC_NODE": 344.4413, "ARG_OF_PERICENTER": 268.3663, "MEAN_ANOMALY": 91.6293, "BSTAR": 0.00041399000000000004, "EPOCH": "2023-09-30T17:45:37"}, {"OBJECT_NAME": "NEUSAR", "NORAD_CAT_ID": 52937, "MEAN_MOTION": 15.07997321, "ECCENTRICITY": 0.0001716, "INCLINATION": 9.9786, "RA_OF_ASC_NODE": 24.8027, "ARG_OF_PERICENTER": 85.5833, "MEAN_ANOMALY": 274.4578, "BSTAR": 0.00069195, "EPOCH": "2023-12-28T07:08:57"}, {"OBJECT_NAME": "CINEMA-3 (KHUSAT-2)", "NORAD_CAT_ID": 39426, "MEAN_MOTION": 14.78011842, "ECCENTRICITY": 0.0090675, "INCLINATION": 97.8433, "RA_OF_ASC_NODE": 346.9945, "ARG_OF_PERICENTER": 162.1567, "MEAN_ANOMALY": 198.2864, "BSTAR": 0.00021754, "EPOCH": "2026-03-13T06:57:51"}, {"OBJECT_NAME": "NUSAT-6 (HYPATIA)", "NORAD_CAT_ID": 46272, "MEAN_MOTION": 16.40036993, "ECCENTRICITY": 0.0013029, "INCLINATION": 97.2026, "RA_OF_ASC_NODE": 336.2175, "ARG_OF_PERICENTER": 264.7707, "MEAN_ANOMALY": 95.2106, "BSTAR": 0.00055612, "EPOCH": "2024-09-13T16:58:59"}, {"OBJECT_NAME": "DTUSAT-2", "NORAD_CAT_ID": 40030, "MEAN_MOTION": 15.13620769, "ECCENTRICITY": 0.0007591, "INCLINATION": 98.085, "RA_OF_ASC_NODE": 64.7507, "ARG_OF_PERICENTER": 185.8583, "MEAN_ANOMALY": 174.2559, "BSTAR": 0.0005200399999999999, "EPOCH": "2026-03-13T22:57:22"}, {"OBJECT_NAME": "NUSAT-12 (DOROTHY)", "NORAD_CAT_ID": 46827, "MEAN_MOTION": 16.36178297, "ECCENTRICITY": 0.0011945, "INCLINATION": 97.1044, "RA_OF_ASC_NODE": 344.9336, "ARG_OF_PERICENTER": 264.565, "MEAN_ANOMALY": 95.4286, "BSTAR": 0.0008634300000000001, "EPOCH": "2023-09-26T20:09:18"}, {"OBJECT_NAME": "NUSAT-4 (ADA)", "NORAD_CAT_ID": 43195, "MEAN_MOTION": 16.38072031, "ECCENTRICITY": 0.0007046, "INCLINATION": 97.5559, "RA_OF_ASC_NODE": 181.2615, "ARG_OF_PERICENTER": 278.8217, "MEAN_ANOMALY": 81.2283, "BSTAR": 0.00073412, "EPOCH": "2024-01-04T03:41:36"}, {"OBJECT_NAME": "NUSAT-9 (ALICE)", "NORAD_CAT_ID": 46828, "MEAN_MOTION": 16.33943729, "ECCENTRICITY": 0.001099, "INCLINATION": 97.0919, "RA_OF_ASC_NODE": 350.4269, "ARG_OF_PERICENTER": 266.8171, "MEAN_ANOMALY": 93.1869, "BSTAR": 0.0009418100000000001, "EPOCH": "2023-10-02T20:48:12"}, {"OBJECT_NAME": "NUSAT-5 (MARYAM)", "NORAD_CAT_ID": 43204, "MEAN_MOTION": 16.4605451, "ECCENTRICITY": 0.0008666, "INCLINATION": 97.5583, "RA_OF_ASC_NODE": 170.606, "ARG_OF_PERICENTER": 279.6992, "MEAN_ANOMALY": 80.3331, "BSTAR": 0.00028268, "EPOCH": "2023-12-24T01:49:10"}, {"OBJECT_NAME": "CHUBUSAT-2", "NORAD_CAT_ID": 41338, "MEAN_MOTION": 15.19817765, "ECCENTRICITY": 0.0008656, "INCLINATION": 30.9967, "RA_OF_ASC_NODE": 226.7504, "ARG_OF_PERICENTER": 182.5168, "MEAN_ANOMALY": 177.543, "BSTAR": 0.00035058, "EPOCH": "2026-03-13T19:40:59"}, {"OBJECT_NAME": "O/OREOS (USA 219)", "NORAD_CAT_ID": 37224, "MEAN_MOTION": 14.93303315, "ECCENTRICITY": 0.0016748, "INCLINATION": 71.9708, "RA_OF_ASC_NODE": 296.7525, "ARG_OF_PERICENTER": 250.1651, "MEAN_ANOMALY": 109.7714, "BSTAR": 0.00026673999999999996, "EPOCH": "2026-03-13T14:48:38"}, {"OBJECT_NAME": "SPOT 5", "NORAD_CAT_ID": 27421, "MEAN_MOTION": 14.54665613, "ECCENTRICITY": 0.0129098, "INCLINATION": 97.9979, "RA_OF_ASC_NODE": 116.0092, "ARG_OF_PERICENTER": 212.1013, "MEAN_ANOMALY": 147.2278, "BSTAR": 0.00010395, "EPOCH": "2026-03-13T23:24:59"}, {"OBJECT_NAME": "SPOT 6", "NORAD_CAT_ID": 38755, "MEAN_MOTION": 14.58545193, "ECCENTRICITY": 0.0001519, "INCLINATION": 98.2212, "RA_OF_ASC_NODE": 141.2962, "ARG_OF_PERICENTER": 92.5216, "MEAN_ANOMALY": 267.6158, "BSTAR": 6.4742e-05, "EPOCH": "2026-03-13T21:49:58"}, {"OBJECT_NAME": "SPOT 7", "NORAD_CAT_ID": 40053, "MEAN_MOTION": 14.60866373, "ECCENTRICITY": 0.0001432, "INCLINATION": 98.0737, "RA_OF_ASC_NODE": 137.8192, "ARG_OF_PERICENTER": 99.1404, "MEAN_ANOMALY": 260.9959, "BSTAR": 9.7991e-05, "EPOCH": "2026-03-13T21:51:07"}, {"OBJECT_NAME": "GLONASS125 [COD]", "NORAD_CAT_ID": 37372, "MEAN_MOTION": 2.13104226, "ECCENTRICITY": 0.000871, "INCLINATION": 64.8285, "RA_OF_ASC_NODE": 104.8188, "ARG_OF_PERICENTER": 293.3373, "MEAN_ANOMALY": 12.0047, "BSTAR": 0.0, "EPOCH": "2023-11-08T23:59:42"}, {"OBJECT_NAME": "JILIN-1 GAOFEN 03D48", "NORAD_CAT_ID": 54695, "MEAN_MOTION": 15.33068034, "ECCENTRICITY": 0.0007644, "INCLINATION": 97.6778, "RA_OF_ASC_NODE": 238.63, "ARG_OF_PERICENTER": 99.1246, "MEAN_ANOMALY": 261.086, "BSTAR": 0.00044999, "EPOCH": "2026-03-13T23:22:13"}, {"OBJECT_NAME": "JILIN-1 GAOFEN 3D28", "NORAD_CAT_ID": 52445, "MEAN_MOTION": 15.60632762, "ECCENTRICITY": 0.0002663, "INCLINATION": 97.5574, "RA_OF_ASC_NODE": 179.5289, "ARG_OF_PERICENTER": 66.9948, "MEAN_ANOMALY": 293.159, "BSTAR": 0.00097274, "EPOCH": "2026-03-13T21:49:31"}, {"OBJECT_NAME": "JILIN-1 GAOFEN 03D14", "NORAD_CAT_ID": 51831, "MEAN_MOTION": 15.81049188, "ECCENTRICITY": 0.0003043, "INCLINATION": 97.3688, "RA_OF_ASC_NODE": 164.6872, "ARG_OF_PERICENTER": 152.8576, "MEAN_ANOMALY": 207.2851, "BSTAR": 0.0011202, "EPOCH": "2026-03-12T06:18:07"}, {"OBJECT_NAME": "JILIN-1 GAOFEN 03D16", "NORAD_CAT_ID": 51834, "MEAN_MOTION": 15.89787455, "ECCENTRICITY": 0.0002752, "INCLINATION": 97.3683, "RA_OF_ASC_NODE": 167.8466, "ARG_OF_PERICENTER": 210.2494, "MEAN_ANOMALY": 149.862, "BSTAR": 0.0012409, "EPOCH": "2026-03-13T22:19:50"}, {"OBJECT_NAME": "JILIN-1 GAOFEN 3C", "NORAD_CAT_ID": 46455, "MEAN_MOTION": 16.4332105, "ECCENTRICITY": 0.0008886, "INCLINATION": 97.224, "RA_OF_ASC_NODE": 102.405, "ARG_OF_PERICENTER": 228.0638, "MEAN_ANOMALY": 131.9907, "BSTAR": 0.00043027, "EPOCH": "2026-02-10T19:53:25"}, {"OBJECT_NAME": "JILIN-1 GAOFEN 03D11", "NORAD_CAT_ID": 51835, "MEAN_MOTION": 15.78195757, "ECCENTRICITY": 0.0003472, "INCLINATION": 97.3721, "RA_OF_ASC_NODE": 164.6089, "ARG_OF_PERICENTER": 168.3789, "MEAN_ANOMALY": 191.7558, "BSTAR": 0.0010862, "EPOCH": "2026-03-12T05:09:01"}, {"OBJECT_NAME": "JILIN-1 GAOFEN 3D", "NORAD_CAT_ID": 46456, "MEAN_MOTION": 15.21343265, "ECCENTRICITY": 0.0011568, "INCLINATION": 97.3728, "RA_OF_ASC_NODE": 46.7737, "ARG_OF_PERICENTER": 112.6941, "MEAN_ANOMALY": 247.5519, "BSTAR": 0.00055382, "EPOCH": "2023-12-28T11:38:25"}, {"OBJECT_NAME": "JILIN-1 GAOFEN 3E", "NORAD_CAT_ID": 46457, "MEAN_MOTION": 15.54182685, "ECCENTRICITY": 0.0015199, "INCLINATION": 97.2426, "RA_OF_ASC_NODE": 123.9773, "ARG_OF_PERICENTER": 150.3093, "MEAN_ANOMALY": 209.9027, "BSTAR": 0.000728, "EPOCH": "2026-03-13T22:48:07"}, {"OBJECT_NAME": "JILIN-1 03", "NORAD_CAT_ID": 41914, "MEAN_MOTION": 15.39113047, "ECCENTRICITY": 0.0007394, "INCLINATION": 97.1997, "RA_OF_ASC_NODE": 81.5648, "ARG_OF_PERICENTER": 140.8128, "MEAN_ANOMALY": 219.3654, "BSTAR": 0.00040647000000000003, "EPOCH": "2026-03-13T23:42:15"}, {"OBJECT_NAME": "JILIN-1 GAOFEN 3D32", "NORAD_CAT_ID": 52449, "MEAN_MOTION": 15.2053231, "ECCENTRICITY": 0.0011601, "INCLINATION": 97.6185, "RA_OF_ASC_NODE": 74.9126, "ARG_OF_PERICENTER": 14.3554, "MEAN_ANOMALY": 345.8008, "BSTAR": 0.00056673, "EPOCH": "2023-12-28T10:45:20"}, {"OBJECT_NAME": "JILIN-1 GAOFEN 03D15", "NORAD_CAT_ID": 51839, "MEAN_MOTION": 15.70184009, "ECCENTRICITY": 0.0003813, "INCLINATION": 97.3687, "RA_OF_ASC_NODE": 164.3937, "ARG_OF_PERICENTER": 164.698, "MEAN_ANOMALY": 195.4398, "BSTAR": 0.0010919, "EPOCH": "2026-03-13T22:49:37"}, {"OBJECT_NAME": "JILIN-1 GAOFEN 3F", "NORAD_CAT_ID": 46458, "MEAN_MOTION": 15.52566429, "ECCENTRICITY": 0.0016742, "INCLINATION": 97.2381, "RA_OF_ASC_NODE": 121.635, "ARG_OF_PERICENTER": 139.6856, "MEAN_ANOMALY": 220.5642, "BSTAR": 0.00070215, "EPOCH": "2026-03-13T21:52:55"}, {"OBJECT_NAME": "JILIN-1 GAOFEN 3G", "NORAD_CAT_ID": 46459, "MEAN_MOTION": 15.58394288, "ECCENTRICITY": 0.0012688, "INCLINATION": 97.2458, "RA_OF_ASC_NODE": 127.2844, "ARG_OF_PERICENTER": 52.8372, "MEAN_ANOMALY": 307.4041, "BSTAR": 0.00076823, "EPOCH": "2026-03-13T22:57:05"}, {"OBJECT_NAME": "JILIN-1 04", "NORAD_CAT_ID": 43022, "MEAN_MOTION": 15.39855409, "ECCENTRICITY": 0.0004764, "INCLINATION": 97.4764, "RA_OF_ASC_NODE": 180.2825, "ARG_OF_PERICENTER": 164.4367, "MEAN_ANOMALY": 195.7026, "BSTAR": 0.00043830000000000003, "EPOCH": "2026-03-13T23:15:06"}, {"OBJECT_NAME": "JILIN-1 GAOFEN 3D33", "NORAD_CAT_ID": 52450, "MEAN_MOTION": 15.20833127, "ECCENTRICITY": 0.0013609, "INCLINATION": 97.6181, "RA_OF_ASC_NODE": 74.9956, "ARG_OF_PERICENTER": 10.9961, "MEAN_ANOMALY": 349.1568, "BSTAR": 0.00056472, "EPOCH": "2023-12-28T10:56:13"}, {"OBJECT_NAME": "JILIN-1 GAOFEN 3H", "NORAD_CAT_ID": 46460, "MEAN_MOTION": 15.56778448, "ECCENTRICITY": 0.0006484, "INCLINATION": 97.2402, "RA_OF_ASC_NODE": 123.983, "ARG_OF_PERICENTER": 347.5654, "MEAN_ANOMALY": 12.5441, "BSTAR": 0.0007107900000000001, "EPOCH": "2026-03-13T21:54:49"}, {"OBJECT_NAME": "JILIN-1 05", "NORAD_CAT_ID": 43023, "MEAN_MOTION": 15.32516093, "ECCENTRICITY": 0.0004951, "INCLINATION": 97.4781, "RA_OF_ASC_NODE": 177.9842, "ARG_OF_PERICENTER": 190.8207, "MEAN_ANOMALY": 169.2929, "BSTAR": 0.00024848000000000003, "EPOCH": "2026-03-13T23:06:06"}, {"OBJECT_NAME": "SBIRS GEO-3 (USA 282)", "NORAD_CAT_ID": 43162, "MEAN_MOTION": 1.00272787, "ECCENTRICITY": 0.0002207, "INCLINATION": 2.1264, "RA_OF_ASC_NODE": 7.356, "ARG_OF_PERICENTER": 350.0556, "MEAN_ANOMALY": 311.1915, "BSTAR": 0.0, "EPOCH": "2026-03-13T19:46:14"}, {"OBJECT_NAME": "SBIRS GEO-4 (USA 273)", "NORAD_CAT_ID": 41937, "MEAN_MOTION": 1.00272716, "ECCENTRICITY": 0.0002291, "INCLINATION": 2.0648, "RA_OF_ASC_NODE": 40.3594, "ARG_OF_PERICENTER": 316.9988, "MEAN_ANOMALY": 136.2516, "BSTAR": 0.0, "EPOCH": "2026-03-13T20:05:01"}, {"OBJECT_NAME": "SBIRS GEO-5 (USA 315)", "NORAD_CAT_ID": 48618, "MEAN_MOTION": 1.00271905, "ECCENTRICITY": 0.0001187, "INCLINATION": 5.2257, "RA_OF_ASC_NODE": 328.3918, "ARG_OF_PERICENTER": 28.3379, "MEAN_ANOMALY": 212.5906, "BSTAR": 0.0, "EPOCH": "2026-03-13T20:16:17"}, {"OBJECT_NAME": "SBIRS GEO-6 (USA 336)", "NORAD_CAT_ID": 53355, "MEAN_MOTION": 1.00271656, "ECCENTRICITY": 0.0002092, "INCLINATION": 3.4222, "RA_OF_ASC_NODE": 315.954, "ARG_OF_PERICENTER": 39.3161, "MEAN_ANOMALY": 298.8075, "BSTAR": 0.0, "EPOCH": "2026-03-13T22:54:04"}, {"OBJECT_NAME": "SBIRS GEO-1 (USA 230)", "NORAD_CAT_ID": 37481, "MEAN_MOTION": 1.00272453, "ECCENTRICITY": 0.0002318, "INCLINATION": 4.3256, "RA_OF_ASC_NODE": 53.0987, "ARG_OF_PERICENTER": 296.7572, "MEAN_ANOMALY": 287.6177, "BSTAR": 0.0, "EPOCH": "2026-03-13T03:39:35"}, {"OBJECT_NAME": "SBIRS GEO-2 (USA 241)", "NORAD_CAT_ID": 39120, "MEAN_MOTION": 1.00271486, "ECCENTRICITY": 0.000228, "INCLINATION": 4.2817, "RA_OF_ASC_NODE": 52.3935, "ARG_OF_PERICENTER": 297.8022, "MEAN_ANOMALY": 281.3772, "BSTAR": 0.0, "EPOCH": "2026-03-13T10:01:21"}, {"OBJECT_NAME": "SKYSAT-C17", "NORAD_CAT_ID": 46179, "MEAN_MOTION": 15.7911991, "ECCENTRICITY": 0.0006126, "INCLINATION": 52.97, "RA_OF_ASC_NODE": 214.8332, "ARG_OF_PERICENTER": 89.9494, "MEAN_ANOMALY": 270.2227, "BSTAR": 0.00064037, "EPOCH": "2023-12-27T20:37:45"}, {"OBJECT_NAME": "SKYSAT-C18", "NORAD_CAT_ID": 46180, "MEAN_MOTION": 16.35747614, "ECCENTRICITY": 0.0017318, "INCLINATION": 52.9561, "RA_OF_ASC_NODE": 11.8431, "ARG_OF_PERICENTER": 265.4879, "MEAN_ANOMALY": 104.1762, "BSTAR": 0.0015942999999999999, "EPOCH": "2023-06-25T20:09:47"}, {"OBJECT_NAME": "SKYSAT-C19", "NORAD_CAT_ID": 46235, "MEAN_MOTION": 15.89514628, "ECCENTRICITY": 0.0002149, "INCLINATION": 52.9675, "RA_OF_ASC_NODE": 201.9813, "ARG_OF_PERICENTER": 132.3648, "MEAN_ANOMALY": 227.7558, "BSTAR": 0.0007014899999999999, "EPOCH": "2023-12-27T23:17:19"}, {"OBJECT_NAME": "SKYSAT-C14", "NORAD_CAT_ID": 45788, "MEAN_MOTION": 15.53833173, "ECCENTRICITY": 0.001113, "INCLINATION": 52.9777, "RA_OF_ASC_NODE": 149.837, "ARG_OF_PERICENTER": 213.0476, "MEAN_ANOMALY": 146.9838, "BSTAR": 0.00062044, "EPOCH": "2023-12-27T15:51:00"}, {"OBJECT_NAME": "SKYSAT-C16", "NORAD_CAT_ID": 45789, "MEAN_MOTION": 15.53303284, "ECCENTRICITY": 0.000551, "INCLINATION": 52.9788, "RA_OF_ASC_NODE": 133.7921, "ARG_OF_PERICENTER": 2.6753, "MEAN_ANOMALY": 357.4284, "BSTAR": 0.0005727, "EPOCH": "2023-12-28T12:24:10"}, {"OBJECT_NAME": "SKYSAT-C15", "NORAD_CAT_ID": 45790, "MEAN_MOTION": 15.47687342, "ECCENTRICITY": 0.0003931, "INCLINATION": 52.9782, "RA_OF_ASC_NODE": 154.0912, "ARG_OF_PERICENTER": 180.8503, "MEAN_ANOMALY": 179.2497, "BSTAR": 0.00058075, "EPOCH": "2023-12-27T15:49:43"}, {"OBJECT_NAME": "SKYSAT-C9", "NORAD_CAT_ID": 42989, "MEAN_MOTION": 15.39018182, "ECCENTRICITY": 0.0009866, "INCLINATION": 97.4262, "RA_OF_ASC_NODE": 208.551, "ARG_OF_PERICENTER": 120.4629, "MEAN_ANOMALY": 239.7592, "BSTAR": 0.00040079, "EPOCH": "2026-03-13T08:30:09"}, {"OBJECT_NAME": "SKYSAT-C5", "NORAD_CAT_ID": 41772, "MEAN_MOTION": 15.3435329, "ECCENTRICITY": 0.0001665, "INCLINATION": 97.0615, "RA_OF_ASC_NODE": 116.5685, "ARG_OF_PERICENTER": 86.9951, "MEAN_ANOMALY": 273.1483, "BSTAR": 0.00028166000000000004, "EPOCH": "2026-03-12T15:07:05"}, {"OBJECT_NAME": "SKYSAT-C2", "NORAD_CAT_ID": 41773, "MEAN_MOTION": 15.398215, "ECCENTRICITY": 0.0004736, "INCLINATION": 97.0279, "RA_OF_ASC_NODE": 98.5898, "ARG_OF_PERICENTER": 59.4654, "MEAN_ANOMALY": 300.706, "BSTAR": 0.00036845, "EPOCH": "2026-03-13T19:15:38"}, {"OBJECT_NAME": "SKYSAT-C3", "NORAD_CAT_ID": 41774, "MEAN_MOTION": 15.48522832, "ECCENTRICITY": 0.0001744, "INCLINATION": 96.9178, "RA_OF_ASC_NODE": 107.5203, "ARG_OF_PERICENTER": 112.5905, "MEAN_ANOMALY": 247.5532, "BSTAR": 0.00047518, "EPOCH": "2026-03-13T19:45:36"}, {"OBJECT_NAME": "SKYSAT-C11", "NORAD_CAT_ID": 42987, "MEAN_MOTION": 15.52704181, "ECCENTRICITY": 4.71e-05, "INCLINATION": 97.4206, "RA_OF_ASC_NODE": 218.0313, "ARG_OF_PERICENTER": 77.4255, "MEAN_ANOMALY": 282.705, "BSTAR": 0.00054886, "EPOCH": "2026-03-13T21:44:48"}, {"OBJECT_NAME": "SKYSAT-C10", "NORAD_CAT_ID": 42988, "MEAN_MOTION": 15.32791548, "ECCENTRICITY": 9.97e-05, "INCLINATION": 97.4337, "RA_OF_ASC_NODE": 209.0417, "ARG_OF_PERICENTER": 94.2944, "MEAN_ANOMALY": 265.8412, "BSTAR": 0.00041338000000000003, "EPOCH": "2026-03-13T21:50:28"}, {"OBJECT_NAME": "SKYSAT-C8", "NORAD_CAT_ID": 42990, "MEAN_MOTION": 15.34894571, "ECCENTRICITY": 0.0001228, "INCLINATION": 97.4354, "RA_OF_ASC_NODE": 208.539, "ARG_OF_PERICENTER": 95.1778, "MEAN_ANOMALY": 264.9605, "BSTAR": 0.0004103, "EPOCH": "2026-03-13T22:53:35"}, {"OBJECT_NAME": "SKYSAT-C7", "NORAD_CAT_ID": 42991, "MEAN_MOTION": 15.3484588, "ECCENTRICITY": 0.0007304, "INCLINATION": 97.4366, "RA_OF_ASC_NODE": 209.5123, "ARG_OF_PERICENTER": 90.9557, "MEAN_ANOMALY": 269.2523, "BSTAR": 0.00042582, "EPOCH": "2026-03-13T22:39:31"}, {"OBJECT_NAME": "SKYSAT-C6", "NORAD_CAT_ID": 42992, "MEAN_MOTION": 15.32609953, "ECCENTRICITY": 0.0003737, "INCLINATION": 97.44, "RA_OF_ASC_NODE": 209.7875, "ARG_OF_PERICENTER": 117.9663, "MEAN_ANOMALY": 242.1957, "BSTAR": 0.00040575, "EPOCH": "2026-03-13T22:43:08"}, {"OBJECT_NAME": "SKYSAT-C12", "NORAD_CAT_ID": 43797, "MEAN_MOTION": 15.45770367, "ECCENTRICITY": 0.0005874, "INCLINATION": 96.9381, "RA_OF_ASC_NODE": 100.1924, "ARG_OF_PERICENTER": 126.9428, "MEAN_ANOMALY": 233.2361, "BSTAR": 0.00040636000000000003, "EPOCH": "2026-03-13T23:11:55"}, {"OBJECT_NAME": "SKYSAT-C13", "NORAD_CAT_ID": 43802, "MEAN_MOTION": 15.77539348, "ECCENTRICITY": 0.0004556, "INCLINATION": 96.9399, "RA_OF_ASC_NODE": 120.5628, "ARG_OF_PERICENTER": 185.5887, "MEAN_ANOMALY": 174.533, "BSTAR": 0.0006055899999999999, "EPOCH": "2026-03-13T21:59:14"}, {"OBJECT_NAME": "SKYSAT-A", "NORAD_CAT_ID": 39418, "MEAN_MOTION": 15.12387974, "ECCENTRICITY": 0.0019985, "INCLINATION": 97.395, "RA_OF_ASC_NODE": 125.2838, "ARG_OF_PERICENTER": 284.9639, "MEAN_ANOMALY": 74.938, "BSTAR": 0.00021779000000000001, "EPOCH": "2026-03-13T20:52:44"}, {"OBJECT_NAME": "SKYSAT-B", "NORAD_CAT_ID": 40072, "MEAN_MOTION": 14.8774521, "ECCENTRICITY": 0.000457, "INCLINATION": 98.3728, "RA_OF_ASC_NODE": 26.3696, "ARG_OF_PERICENTER": 217.1835, "MEAN_ANOMALY": 142.9064, "BSTAR": 0.00023938, "EPOCH": "2026-03-13T18:21:32"}, {"OBJECT_NAME": "SKYSAT-C1", "NORAD_CAT_ID": 41601, "MEAN_MOTION": 15.34599505, "ECCENTRICITY": 0.0003252, "INCLINATION": 96.9701, "RA_OF_ASC_NODE": 109.504, "ARG_OF_PERICENTER": 45.2329, "MEAN_ANOMALY": 314.9179, "BSTAR": 0.00033023000000000004, "EPOCH": "2026-03-13T13:09:19"}, {"OBJECT_NAME": "PLEIADES NEO 3", "NORAD_CAT_ID": 48268, "MEAN_MOTION": 14.81671937, "ECCENTRICITY": 0.000128, "INCLINATION": 97.893, "RA_OF_ASC_NODE": 149.098, "ARG_OF_PERICENTER": 94.2351, "MEAN_ANOMALY": 265.9009, "BSTAR": 2.3185000000000002e-05, "EPOCH": "2026-03-13T23:09:22"}, {"OBJECT_NAME": "PLEIADES NEO 4", "NORAD_CAT_ID": 49070, "MEAN_MOTION": 14.81671436, "ECCENTRICITY": 0.0001336, "INCLINATION": 97.893, "RA_OF_ASC_NODE": 149.0607, "ARG_OF_PERICENTER": 92.4826, "MEAN_ANOMALY": 267.654, "BSTAR": -7.0122e-05, "EPOCH": "2026-03-13T22:20:43"}, {"OBJECT_NAME": "PLEIADES 1B", "NORAD_CAT_ID": 39019, "MEAN_MOTION": 14.58530816, "ECCENTRICITY": 0.0001594, "INCLINATION": 98.2006, "RA_OF_ASC_NODE": 149.2705, "ARG_OF_PERICENTER": 84.011, "MEAN_ANOMALY": 276.127, "BSTAR": 7.3644e-05, "EPOCH": "2026-03-13T22:17:39"}, {"OBJECT_NAME": "PLEIADES 1A", "NORAD_CAT_ID": 38012, "MEAN_MOTION": 14.58543149, "ECCENTRICITY": 0.0001693, "INCLINATION": 98.2035, "RA_OF_ASC_NODE": 149.3549, "ARG_OF_PERICENTER": 87.1605, "MEAN_ANOMALY": 85.9887, "BSTAR": 3.6172e-05, "EPOCH": "2026-03-13T23:54:34"}, {"OBJECT_NAME": "PLEIADES YEARLING", "NORAD_CAT_ID": 56207, "MEAN_MOTION": 15.36797276, "ECCENTRICITY": 0.0012954, "INCLINATION": 97.388, "RA_OF_ASC_NODE": 256.6744, "ARG_OF_PERICENTER": 51.7533, "MEAN_ANOMALY": 308.4875, "BSTAR": 0.0010478, "EPOCH": "2023-12-28T09:58:50"}, {"OBJECT_NAME": "CSO-3", "NORAD_CAT_ID": 63156, "MEAN_MOTION": 14.34022377, "ECCENTRICITY": 0.0001932, "INCLINATION": 98.606, "RA_OF_ASC_NODE": 14.3262, "ARG_OF_PERICENTER": 17.427, "MEAN_ANOMALY": 342.6981, "BSTAR": 0.00016071, "EPOCH": "2025-03-13T22:37:36"}]